[{"channelId":"UCJdThrvpDDNpYNyxYhM6UKQ","publishedAt":"2017-03-09T15:50:42.000Z","title":"වික්ටර් රත්නායක නව යුවල විවාහයෙන් පසු  සහභාගී  වුනු මුල්ම මංගල්යෝත්සවය","description":"නැරබුවාට ස්තුතියි ..කරුණාකර SUBSCRIBE බටනය Click කර \nසහ Comment \/ Like කර අපේ චැනලයට සහයෝගය දක්වන්න.","viewCount":"1076272","likeCount":"1387","dislikeCount":"940","commentCount":"310","tags":["sinhala cinema","sinhala films","sinhala movies","sinhala gossip","sinhala sex","sinhala porn","sinhala xxx","sinhala news","srilankan cinema","Sidu","Iraj","iraj ashawaree","Ashawaree","derana tv","sinhala tele drama","gossip lanka","web gossip","victor rathnayaka","victor rathnayaka wedding","victor rathnayaka new wife","victor rathnayaka wife","hiru gossip","victor wife","cricket highlights","srilanka cricket","naifm","gossip king","lelum rathnayaka","victor rathnayaka new photos"],"thumbnailUrl":"https:\/\/i.ytimg.com\/vi\/PGXT76c6E4c\/hqdefault.jpg","category":"O","sentiment":"P","comments":[{"id":"UgxqxghQF2QTYEJvAsl4AaABAg","comment":"Yaluwane mawa subscribe karala support ekak denna","author":"Su Perera","likeCount":0,"totalReplyCount":0,"publishedAt":"2019-10-14T12:56:38.000Z","replies":[]},{"id":"UgyZb01cPkxSc1r8fat4AaABAg","comment":"අපට මොකෝ අනේ","author":"geetha damyanthi","likeCount":0,"totalReplyCount":1,"publishedAt":"2019-07-14T18:01:02.000Z","replies":[{"parentId":"UgyZb01cPkxSc1r8fat4AaABAg","authorDisplayName":"Srini Perera","replyComment":"වික්ටර්ගේ සින්දුත් අහන්න ඒපා උනා මේ මගූලෙන්.","publishedAt":"2019-07-16T02:21:04.000Z","likeCount":0}]},{"id":"UgwpuQIW5sCIhc2UXrJ4AaABAg","comment":"Ohuge tAruna kama waydi wela hodai hoda kalakaruwek","author":"Chalana Tattoo","likeCount":0,"totalReplyCount":0,"publishedAt":"2019-06-28T17:51:28.000Z","replies":[]},{"id":"UgzNfQj9sszHr0V3p8x4AaABAg","comment":"දසුන්ගේ විස්තර ලියන්න ලියන්එයාගෙ අම්මටයි බිරිදටයි තමයි දුක දසුනුත් වසර 15ක් අමතක කරලනෙ ටික කාලෙකට මුනගසුන චලනි නිශා ඒත් චලනිටත් බොරු කරල බිරිදට චපල වෙලා කොහොමත්","author":"Siryani Wikramasooriya","likeCount":0,"totalReplyCount":0,"publishedAt":"2018-09-11T09:02:19.000Z","replies":[]},{"id":"UgykGv9kEl9cr2OjIwZ4AaABAg","comment":"Danna ona amataka nowana daduwamak makita 😭😭😭😭😭","author":"shanika madushani شا","likeCount":0,"totalReplyCount":0,"publishedAt":"2018-01-11T07:47:03.000Z","replies":[]},{"id":"UgyxPXVghtxTP8PYSGt4AaABAg","comment":"Darupaulak ganiyek nisa amathaka kala meyage prema geeth motada wadakarana thanata wancha kala gani meyata Mona karaida","author":"erandathi randeniya","likeCount":0,"totalReplyCount":0,"publishedAt":"2018-01-10T12:19:10.000Z","replies":[]},{"id":"UgyES4vY7Gpj6EkoFaF4AaABAg","comment":"Oita wadiya horen jara wada karana gayakayo kochchara innawada mata nan meke kisi waradak penne na","author":"Anil Hettiarachchi","likeCount":0,"totalReplyCount":0,"publishedAt":"2017-12-24T15:32:53.000Z","replies":[]},{"id":"UgzgzSnCacMvNg3mDKh4AaABAg","comment":"kawesa","author":"Dulanjali Madushani","likeCount":0,"totalReplyCount":0,"publishedAt":"2017-11-11T06:33:39.000Z","replies":[]},{"id":"UgwPJfol2vE2XknJXNB4AaABAg","comment":"Love  has no age limit .The heart  wants what  it wants. Congratulation!","author":"S Jayasuriya","likeCount":0,"totalReplyCount":0,"publishedAt":"2017-10-21T20:06:54.000Z","replies":[]},{"id":"UgwjIF3iLRna8MT4fiV4AaABAg","comment":"You can strat a new life at any  age.","author":"S Jayasuriya","likeCount":0,"totalReplyCount":0,"publishedAt":"2017-10-21T19:52:10.000Z","replies":[]},{"id":"UgxPxWSesgB96dYFd8V4AaABAg","comment":"loku wayasa parathrayak nam penne naha. oba depalata mama suba pathanawa. hangi haora nathiwa thamage kemeththa eli daraw karanna sakthiyak labeema godak watinawa.","author":"Donzmahi1 Gmail. com Donna Hett","likeCount":0,"totalReplyCount":0,"publishedAt":"2017-10-04T08:04:53.000Z","replies":[]},{"id":"UgyvNF6uakmuHmfeBdR4AaABAg","comment":"This is not big deal, problem is that others are  interfering their private life.  Typical mind set of most of Sri Lankans' mind  designed to interfere others  stuffs.","author":"ThAriNdU SeRaM","likeCount":0,"totalReplyCount":0,"publishedAt":"2017-08-10T10:39:47.000Z","replies":[]},{"id":"Ugi5iQ_xEZsuNHgCoAEC","comment":"kisima gataluwak nee","author":"SUNIL PREMACHANDRA","likeCount":0,"totalReplyCount":0,"publishedAt":"2017-06-11T09:47:16.000Z","replies":[]},{"id":"UggwzCaf_WyhKngCoAEC","comment":"My warm wishers to your new marriage life. ENJOY...............GOOD LIFE.","author":"Paul Pemraj Ekanayake","likeCount":0,"totalReplyCount":0,"publishedAt":"2017-06-11T08:18:31.000Z","replies":[]},{"id":"UghB9Kpv09sJT3gCoAEC","comment":"Meke apahasa karala thiyenne okkoma theresa mauthumiya wage kanthawo.santhuwarayo wage pirimi.ane ithin ape rate ei me daram duushana ???","author":"Tushari K.A.","likeCount":0,"totalReplyCount":0,"publishedAt":"2017-06-10T19:54:07.000Z","replies":[]},{"id":"UggE0a3v_z0OyHgCoAEC","comment":"ප්‍රස්නයක් නෑ ඉතින් ඒක එයාගෙ පුද්ගලික කැමැත්ත","author":"Bilma roshani","likeCount":0,"totalReplyCount":0,"publishedAt":"2017-05-27T11:19:18.000Z","replies":[]},{"id":"Ugj2h-bbUTaXs3gCoAEC","comment":"this u r like  the u  r happy  &whats hapaning the pepole  you 2 so great beautiful love","author":"Nassir Koyakoty","likeCount":0,"totalReplyCount":0,"publishedAt":"2017-05-14T21:18:22.000Z","replies":[]},{"id":"Uggv6bJrfoqmAHgCoAEC","comment":"eka eyage ardarene","author":"Sanjaya Alahakoon","likeCount":0,"totalReplyCount":0,"publishedAt":"2017-05-08T15:18:12.000Z","replies":[]},{"id":"UghpxuTRx2bUtXgCoAEC","comment":"😀😀😀😀😀😀😀😀😀","author":"renuka madumali","likeCount":0,"totalReplyCount":0,"publishedAt":"2017-05-07T16:21:23.000Z","replies":[]},{"id":"UgiRHgJuUNRgJngCoAEC","comment":"සල්ලිවලට තියන පෙරේත කමට නාකි ම නාකියෙක් ඵක්ක ලගින්නට තරම් පහත් මනසක් ඇති රොඩී කුලේ රොඩිච්චියක් නාකි විසේ ගෙටත් උසේ නහින දෙහින ටිකට පිනක් දහමක් කරගෙන ඉන්නේ නැතුව හෙට අනිද්දා  තියන දේපල ටික අතගාගෙන වටේටම අල්ලනකොට ඕකට මතක් වෙයි දෙයියන් බුදුනුයි දරැ මුනුබුරොයි අබුද්දස්සගෙ කාලේ ලබුත් තිත්තයිලු රාලේ","author":"Damaki Kw","likeCount":4,"totalReplyCount":1,"publishedAt":"2017-05-04T13:58:44.000Z","replies":[{"parentId":"UgiRHgJuUNRgJngCoAEC","authorDisplayName":"Chalana Tattoo","replyComment":"Irsiyawe pelana me vage menissu ae kalakaruvage tava tava haylitaval dunu wenna patanne ae mhathtaysge sendu podi kale idan hanava ae nona kochchara vasanavantsida","publishedAt":"2019-06-28T17:53:24.000Z","likeCount":0}]},{"id":"Uggu-XBinUmk-3gCoAEC","comment":"victor aiya vala marunath ala bahinawa  nam thawa monawada","author":"Prasantha Perera","likeCount":0,"totalReplyCount":0,"publishedAt":"2017-04-18T18:02:04.000Z","replies":[]},{"id":"Ugi7q-JRDdgNZngCoAEC","comment":"madana vise  getath use.","author":"Silva Janaka","likeCount":1,"totalReplyCount":0,"publishedAt":"2017-04-13T08:32:10.000Z","replies":[]},{"id":"Ugi1T-0Lxw-szHgCoAEC","comment":"wish u all the best,,,","author":"dilrukshi lanka","likeCount":0,"totalReplyCount":0,"publishedAt":"2017-04-10T18:08:17.000Z","replies":[]},{"id":"UghdAdJx83s8v3gCoAEC","comment":"naki vise getath u se kiyanne okata thmai","author":"Thanuka Prasad","likeCount":1,"totalReplyCount":0,"publishedAt":"2017-04-09T17:15:26.000Z","replies":[]},{"id":"UgjONj_zgxaXvngCoAEC","comment":"Ane anunge dewal hoyanna apa ayalage kamaththane a miniha nakewelath balaganna kenek ennawane","author":"wasa gunathilake","likeCount":0,"totalReplyCount":0,"publishedAt":"2017-04-07T07:43:11.000Z","replies":[]},{"id":"UggSqi-PdJergXgCoAEC","comment":"very nice voice sir","author":"Nadika Disanayaka","likeCount":0,"totalReplyCount":0,"publishedAt":"2017-04-07T02:23:12.000Z","replies":[]},{"id":"UgyUtBYvTP8fnElEIjV4AaABAg","comment":"ලිද මගේනම්  මන් ලිදෙනම් කාටවත් ai වේදනා...","author":"Pradeep Kumara","likeCount":0,"totalReplyCount":0,"publishedAt":"2017-03-29T18:32:42.000Z","replies":[]},{"id":"Ugw3FIuJDsS-bJCcRp94AaABAg","comment":"vivaha sahathike gaththa wage marana sahathiketh lagadima aran kelinma apayata thamai","author":"Thamara Kumari Abeykoon","likeCount":0,"totalReplyCount":0,"publishedAt":"2017-03-26T12:59:52.000Z","replies":[]},{"id":"UgiZaL_HMo4tyHgCoAEC","comment":"patta machin😂","author":"Nishadi Lakshika","likeCount":0,"totalReplyCount":0,"publishedAt":"2017-03-17T13:58:37.000Z","replies":[]},{"id":"UggG2werQCGRUHgCoAEC","comment":"Me ganita dan watema  inna kollo tika  hukai,,,,Salli walata peretha wesi","author":"Nil Ahasa","likeCount":0,"totalReplyCount":0,"publishedAt":"2017-03-17T02:08:14.000Z","replies":[]},{"id":"UgipVuBYC6AISngCoAEC","comment":"නව යුවලට සුබ පැතුමි\nදරැවෙක් හදන්නpl \nall the best","author":"Nanayakkara Premathilaka Ranjith","likeCount":0,"totalReplyCount":0,"publishedAt":"2017-03-16T18:32:06.000Z","replies":[]},{"id":"UghZvRGy39_bM3gCoAEC","comment":"lajjai victer.mata oya gana tibba gaurawaya nathi karagatta.oya maha wal poosek.thama inna ba neda?lajjai naki tela","author":"Dulan Abeysekera","likeCount":0,"totalReplyCount":0,"publishedAt":"2017-03-16T13:24:02.000Z","replies":[]},{"id":"UgixwUj7a1EXlHgCoAEC","comment":"සින්දුව දැම්මානම් එල","author":"නිෂාන් සුගතදාස Nishan Sugathadasa","likeCount":0,"totalReplyCount":0,"publishedAt":"2017-03-15T19:53:25.000Z","replies":[]},{"id":"UgjahVRnHglzgngCoAEC","comment":"What the hell, Its their life. Let them to make their own decisions and enjoy their privacy .","author":"Harindra Tennakoon","likeCount":0,"totalReplyCount":0,"publishedAt":"2017-03-15T16:41:08.000Z","replies":[]},{"id":"UggRPSmXV8HMq3gCoAEC","comment":"meka puduma lokayak","author":"Nayana Siriwardana","likeCount":0,"totalReplyCount":0,"publishedAt":"2017-03-15T14:08:07.000Z","replies":[]},{"id":"UgggkOhrkNifTHgCoAEC","comment":"Naakiwenako lejjaawa iwarai.  \ndaru munupurange kaalaya iwarai\n\nonna wenasa.\nredi andinne lejjaawata nemei shikkk..","author":"Mallika Mallika","likeCount":0,"totalReplyCount":0,"publishedAt":"2017-03-15T07:36:51.000Z","replies":[]},{"id":"Ugj-KxPUsR5kkngCoAEC","comment":"Naki manamaalaya.wala payai goda payai.heta anidda oya ganith daala yanna wenne wala pallata wili lajjawath aran. dukai apitath.api godak adare karapu gayakayek nisa. oya badagaththe urumei karumei dekama neda","author":"Thamara Kumari Abeykoon","likeCount":0,"totalReplyCount":0,"publishedAt":"2017-03-14T22:11:08.000Z","replies":[]},{"id":"UggmL3nd-JC6MngCoAEC","comment":"ape unta me wage dewal hoya hoya hitapuwama ati.anith dewal ballata giyath kamak na.","author":"PaTta KolLA","likeCount":0,"totalReplyCount":0,"publishedAt":"2017-03-14T20:17:56.000Z","replies":[]},{"id":"UgjFmpw3y1c08ngCoAEC","comment":"Samaharawita me de ape sirith wirith walata nogalapeemak wenna puluwan.. eath api katawath ona widiyata jeewath wenna awashya naa.. rate minissu balan inne anunge dewal wiwechanaya karanna misak thmange deyak hariyata karanna nemei.. mage hadawathinma wictor mahaththayata suba pathanawa","author":"chamike jayathissa","likeCount":0,"totalReplyCount":0,"publishedAt":"2017-03-14T17:57:54.000Z","replies":[]},{"id":"UghKX6kS2N10-XgCoAEC","comment":"Ela Victor Ela...","author":"anjuladias","likeCount":1,"totalReplyCount":0,"publishedAt":"2017-03-14T09:30:39.000Z","replies":[]},{"id":"UghiZhgePXuV13gCoAEC","comment":"ආදරයට වයසක් නැත","author":"Sandaya Kumari","likeCount":6,"totalReplyCount":1,"publishedAt":"2017-03-14T08:01:30.000Z","replies":[{"parentId":"UghiZhgePXuV13gCoAEC","authorDisplayName":"Kasun Harshana","replyComment":"adarayak tyeda","publishedAt":"2017-04-08T23:33:18.000Z","likeCount":0}]},{"id":"UghyWH5QIiwIEHgCoAEC","comment":"lankawe.  colture. eka mokada.   ane naki ponnayo.    Dan. okita.  lamek. hadala.    kamata.  yer. 15.  wenakota.      too.   koheda.  gas ponnayo.","author":"Candana Perera","likeCount":0,"totalReplyCount":0,"publishedAt":"2017-03-14T07:27:32.000Z","replies":[]},{"id":"UgjX3XAGnu2TY3gCoAEC","comment":"sunil perera mhatmya\n ohoma kranm minissu kohoma banida....","author":"íEnVy","likeCount":0,"totalReplyCount":0,"publishedAt":"2017-03-14T01:12:22.000Z","replies":[]},{"id":"UgjPSAZdoezKtngCoAEC","comment":"Who are we to judge? It is in fact extremely rare for someone to obtain conditions for happiness and be happy in samsara. So when it happens it is very appropriate to rejoice from deep within. May they find peace and happiness.","author":"Sandhya U","likeCount":0,"totalReplyCount":0,"publishedAt":"2017-03-13T20:51:51.000Z","replies":[]},{"id":"UgjTffl5CwP3eXgCoAEC","comment":"Congratulations and all the best. Need not to follow the traditions and it is matter of Unconditional love, understanding, trust and sacrifice. Cheers !","author":"Sampath DE SILVA","likeCount":0,"totalReplyCount":0,"publishedAt":"2017-03-13T13:08:53.000Z","replies":[]},{"id":"UghwN6gu8JkZuHgCoAEC","comment":"Supeeeeeer","author":"Paulin Marku","likeCount":0,"totalReplyCount":0,"publishedAt":"2017-03-13T10:29:37.000Z","replies":[]},{"id":"UgjGVdoSndmQSHgCoAEC","comment":"pathagena enaa hatii thamaa ....sathutin ennaa ..suba mangalamm ...\n...","author":"nilukshan iresha","likeCount":0,"totalReplyCount":0,"publishedAt":"2017-03-13T09:59:34.000Z","replies":[]},{"id":"UgggqS6XhBZW6ngCoAEC","comment":"oya dannata suba gaman suba mangalam","author":"Renu disanayaka","likeCount":0,"totalReplyCount":0,"publishedAt":"2017-03-13T06:22:58.000Z","replies":[]},{"id":"Ugg8EfR9fraYq3gCoAEC","comment":"හොරා අපි කාටවත් කියන්නැතුව හොරෙන්ම බැඳගත්තා නේද? පොඩි කොල්ලා රෙද්ද ගලෝන කම්ම හිටියා නේද මේවා දාන්න. එතකම් ටී වී එකට ඇවිල්ලා සදාචාරේ අරවා මේවා කිව්වා නේද? හොරා... නීල බිඟු කැළ කිය කියා අපට කිව්වෙ මේකයි නේද? කොල්ලා මේක එලියට දැම්මෙ නැත්තම් ඔයා තාම \"ඈතින් ඈතට පා නගලා ගණ වනන්තරේ මල්ගොමුවේ අතරමන් වෙවී \" ඉන්දීයි. \nමම නම් ඔයාගේ මේ වැඩේට විරුද්ධ නෑ. ඒත් බැන්ද දවසේ රසික අපට නොකියපු එකට දුකයි අප්පා. ෆ්‍රෙඩී සිල්වාත් ඔහොම බැන්දා ඒත් අපි දන්නෙ එයා පැරලයිස් වෙලා ගෙදර ගෙනත් අතෑරියයින් පස්සෙ. දැන් නම් ඉතින් ලෙලුමා කළ වැඩෙන් අඩු ගානේ ඒක වෙන එකක් නෑ,\nආයේ යන්න එපා අප්පා සිංහල සංස්කෘතිය ගැන කතා කරන්න. එතන හීනි අවුලක් තියනවා වගෙ නෙ නේද? මොකද ඉතින් ජූජකයා අමිත්තතපාව බැන්ද එක මාර නෝමල් නෑනේ අපේ සිංහල සංස්කෘතියේ.ඒත් ඔයා හැන්ඩියා ජූඅක වගේ නෙවෙයි. කෙස් ගහක් වත් ඉදිලා නෑනේ අප්පා.","author":"layaback","likeCount":0,"totalReplyCount":0,"publishedAt":"2017-03-13T04:06:48.000Z","replies":[]},{"id":"UggjJe6r95GfyngCoAEC","comment":"එයාලාට  හොදයි  නම් අපිට මොකො  අප්පා","author":"Don Shani","likeCount":12,"totalReplyCount":2,"publishedAt":"2017-03-13T04:01:56.000Z","replies":[{"parentId":"UggjJe6r95GfyngCoAEC","authorDisplayName":"නිෂාන් සුගතදාස Nishan Sugathadasa","replyComment":"අනිවාරයෙන්. අපට මොකද?","publishedAt":"2017-06-09T07:12:35.000Z","likeCount":0},{"parentId":"UggjJe6r95GfyngCoAEC","authorDisplayName":"wekara yas","replyComment":"Don Shani mokada karanne","publishedAt":"2017-05-04T16:26:18.000Z","likeCount":0}]},{"id":"Ugg6ig_qB5qLrngCoAEC","comment":"නාකි වෙනකොට ආශාවන් එලිදැක්වීමක් වෙන්න ඇති. අනිත් පිරිමින්ටත් ලැජ්ජාවක්. මතු තරුන පරපුරට අවවාද දෙන්න අය නැහැ.  ලැජ්ජ නැති මිනිස්සු නිසා දවසින් දවම පිරිහෙන රට තවත් පිරිහෙනව.","author":"Mallika Mallika","likeCount":0,"totalReplyCount":0,"publishedAt":"2017-03-12T22:43:39.000Z","replies":[]},{"id":"UgjSlaSjbJ_FGngCoAEC","comment":"ලැජජ නැති මගුල්. දරුවන්ගෙ අදෝනාව..","author":"Mallika Mallika","likeCount":0,"totalReplyCount":2,"publishedAt":"2017-03-12T22:33:09.000Z","replies":[{"parentId":"UgjSlaSjbJ_FGngCoAEC","authorDisplayName":"Theekshana Hemanga","replyComment":"I","publishedAt":"2018-10-02T02:46:09.000Z","likeCount":0},{"parentId":"UgjSlaSjbJ_FGngCoAEC","authorDisplayName":"Srilanka Mallika","replyComment":"Mallika Mallika sideu","publishedAt":"2017-06-15T18:17:50.000Z","likeCount":0}]},{"id":"Uggya-cc_4NmaXgCoAEC","comment":"Name of the music pls","author":"Shalma Sultansrilnkacanall","likeCount":0,"totalReplyCount":0,"publishedAt":"2017-03-12T22:21:03.000Z","replies":[]},{"id":"Ugh6vGD__9NhNHgCoAEC","comment":"kohma unath daruwo genath tikak hithuwanam thamai hoda","author":"seetha irenghani","likeCount":0,"totalReplyCount":0,"publishedAt":"2017-03-12T22:05:52.000Z","replies":[]},{"id":"UgiIvkkPQOse-HgCoAEC","comment":"LOOKS LIKE VICTOR IS FALLEN to a gold (money) digging whore..........!!.SAD !!!","author":"Nimal Jayasiri","likeCount":0,"totalReplyCount":0,"publishedAt":"2017-03-12T17:57:25.000Z","replies":[]},{"id":"UggZzjzqllApdHgCoAEC","comment":"පල පල පොනයා  අනුනගෙ දෙවල හොයනනෙ  එ මනුස්සයාගෙ පයට පැගෙන දුවිල්ලක ල තෝපි තෝග සෙරම සමපුරනයිද තෝමෙහෙම මෙ  මනුසයා ගැන දනනෙ තිරිසනනු","author":"Noora Al","likeCount":1,"totalReplyCount":0,"publishedAt":"2017-03-12T17:47:50.000Z","replies":[]},{"id":"Uggc1vu352G_mngCoAEC","comment":"elazzzzzzzzzzzzzzzzzzzzzzzzzzzzzzzzzz","author":"prasanna sameera","likeCount":0,"totalReplyCount":0,"publishedAt":"2017-03-12T13:58:04.000Z","replies":[]},{"id":"UghzEHs0wFC9I3gCoAEC","comment":"බොරැවට මෙිවා අන්තර්ජාලයට මුදා හරින්න එපා   මෝඩයෙක් වගේ මොනව කරත් රටෙි පිලිගත් කෙනෙක් මෙිවා සමාන්‍ය දෙයක්  පොඩි මිනිස්සුන්ට උනාම මෙිවා දානවද  අන්තර්ජාලයට නැනේ ආපුරැවට පවුල් අරවුල් විසදගන්නව මොඩ කම සේල් කර ගන්න එපා ලෝකේටම කියලා","author":"Samantha Disanayaka","likeCount":1,"totalReplyCount":0,"publishedAt":"2017-03-12T13:28:15.000Z","replies":[]},{"id":"UgicLJXXagY2K3gCoAEC","comment":"ගැනිටම  දොස් කියන්න එපා දරැවා තාත්තා හරියට හිටියනම් ඔවා වෙනවද ⁣ තාත්තාත් කැමති නිසානේ","author":"Samantha Disanayaka","likeCount":0,"totalReplyCount":0,"publishedAt":"2017-03-12T13:24:31.000Z","replies":[]},{"id":"UggUjGWIEvfPy3gCoAEC","comment":"අපේ රටෙි මිනිස්සු තනි කර කෙලින්නේ පිස්සු","author":"Samantha Disanayaka","likeCount":3,"totalReplyCount":0,"publishedAt":"2017-03-12T13:23:26.000Z","replies":[]},{"id":"UggDK7q-yFxi_HgCoAEC","comment":"Mama nam waradak dakinna, waif ne, thamange deyak hari kiyanna kenak inna ona. thamange kamththa, lady ta nam 55 penwa, awurudu 33 kenak married weida wikter Rathnayaka. ..wish the marriage","author":"MANJULA MALIK","likeCount":0,"totalReplyCount":0,"publishedAt":"2017-03-12T11:51:22.000Z","replies":[]},{"id":"UggwhopbWW8uvHgCoAEC","comment":"rate  wadgth  bank hadgthu .prsidda mne wage minisunta me mokda wela thiyene  Maru katha samhra AYA kiyane .waysta giyahm daryruwo ene salkna .EA Moda katha mniyameta hititi waysata Yan untah ai kasada badina wada sunoth aiyo mewata kiyan sinhala wachna na","author":"Surangi Preethi","likeCount":0,"totalReplyCount":1,"publishedAt":"2017-03-12T11:28:03.000Z","replies":[{"parentId":"UggwhopbWW8uvHgCoAEC","authorDisplayName":"Surangi Preethi","replyComment":"EA Moda katha monawada \nwaysata Yan seram unta kasada badina aduways kara ganugan EAD dunoth.lankwata thwa hodata thiyevi .ganu Dan gan one laji ape rate wadgth prasida minisu Karan awat.unata nithiyk na API laja wenwa ape UN Karan dewal walta lankwata deviynee pihiti","publishedAt":"2017-03-12T11:30:44.000Z","likeCount":0}]},{"id":"UgglKe-gkRa4ongCoAEC","comment":"hoda 33 hariyatama 55yi. ala goniya wage","author":"tak tuk","likeCount":0,"totalReplyCount":0,"publishedAt":"2017-03-12T11:27:48.000Z","replies":[]},{"id":"UghNnex5_iiW8ngCoAEC","comment":"akane apita 7k badenna nethiyen eda thiyanne,, ethakota paw' vada kari' vada nahi  salli thamai oona ...nictor mama ta  salli thiyanawa''","author":"muhammed maushard mashood ahamed","likeCount":0,"totalReplyCount":0,"publishedAt":"2017-03-12T09:59:35.000Z","replies":[]},{"id":"Ugj5gAeSOjKMS3gCoAEC","comment":"yako'' thiyagena in nawata wada marry karapu eka smart wedak","author":"muhammed maushard mashood ahamed","likeCount":0,"totalReplyCount":0,"publishedAt":"2017-03-12T09:55:46.000Z","replies":[]},{"id":"UggR5FavARSvIngCoAEC","comment":"mad man in wikter toooo fuaaaakkkkkkkk","author":"Ishadi Malisha","likeCount":0,"totalReplyCount":0,"publishedAt":"2017-03-12T08:24:40.000Z","replies":[]},{"id":"UghRsnThhUup83gCoAEC","comment":"enna ennm a me lanka we  sanskruthiya vnasawenwaa","author":"Filushz Fernandz","likeCount":0,"totalReplyCount":0,"publishedAt":"2017-03-12T07:35:48.000Z","replies":[]},{"id":"Ugh5i_nLNe7-F3gCoAEC","comment":"wiktage ke..... m apita moko redda","author":"පැතුම් සුලෝචන විරක්කෝඩි","likeCount":0,"totalReplyCount":0,"publishedAt":"2017-03-12T07:25:54.000Z","replies":[]},{"id":"UgjMajkWiS4W3HgCoAEC","comment":"Jeewithaye weda bari samaye thama daruwanta himiviya yuthu koti 5 Thama weda beri kaamaya  wenuwen para sthree sewanayata yedaweeya......","author":"anjanasj","likeCount":0,"totalReplyCount":0,"publishedAt":"2017-03-12T04:17:41.000Z","replies":[]},{"id":"UgjFEE2NmjaYv3gCoAEC","comment":"Jaya.wewa Jaya Vivah","author":"Victor johnnixon Johnnixon","likeCount":0,"totalReplyCount":0,"publishedAt":"2017-03-12T04:17:03.000Z","replies":[]},{"id":"UgiQP7zUNgRBcHgCoAEC","comment":"subha mangalam lokka","author":"Aravinda Patabandi","likeCount":0,"totalReplyCount":0,"publishedAt":"2017-03-11T23:32:45.000Z","replies":[]},{"id":"Ugh4sUObQ_XxQHgCoAEC","comment":"nice couple","author":"sedwardltp","likeCount":0,"totalReplyCount":0,"publishedAt":"2017-03-11T22:38:00.000Z","replies":[]},{"id":"Ugjte_Z-_AOdJ3gCoAEC","comment":"apy,,un,,anunge,,kunu,,hoynne,,netva,,hetapn,,apy,,lankve,,kollo,,18,,,kollo,,,aurdu,,60,,ganuth,,,ekka,,budiyla,,yanne,,kellith,,,enne,,a vage,,,,yana,,aya,,bolage,,,salli,yanvda,,bun,,,anuge,,kunu,,hoynne,,,","author":"Zebiba Yimam","likeCount":0,"totalReplyCount":0,"publishedAt":"2017-03-11T20:16:18.000Z","replies":[]},{"id":"UgiMpi5KT3Igf3gCoAEC","comment":"tathhai duwai bandath waradak naha neda","author":"ranjith hewage","likeCount":0,"totalReplyCount":0,"publishedAt":"2017-03-11T19:12:58.000Z","replies":[]},{"id":"Ugj4k0eBfN4_93gCoAEC","comment":"වයසෙ වෙනසක් නම් පේන්නේ නෑ. කොහොමත් ඉතින් එයාලගේ කැමැත්තනේ","author":"niluka  jayawardhana.","likeCount":2,"totalReplyCount":0,"publishedAt":"2017-03-11T19:07:38.000Z","replies":[]},{"id":"UghDLrxzH7RSRXgCoAEC","comment":"ayata kemati de ne karanna apita mokada ane ayalai jiwath wenna  etin","author":"Erosani Kumari","likeCount":1,"totalReplyCount":0,"publishedAt":"2017-03-11T18:48:01.000Z","replies":[]},{"id":"Ugi0LD5QddheI3gCoAEC","comment":"super","author":"T R Weeravardana","likeCount":0,"totalReplyCount":0,"publishedAt":"2017-03-11T18:30:13.000Z","replies":[]},{"id":"UgiuLyTNm8yZS3gCoAEC","comment":"math subapathanawa ekemma eth wayasata galapena kenek hoya gatthanam oita wada hodai kiyala matanam hithanne anith eka meyage penumennam meya vikta sir ta lan wela thiyenne salli walata wagema janappriya tjawayata....","author":"Aturugiriyage don Nimal jayawardana","likeCount":0,"totalReplyCount":0,"publishedAt":"2017-03-11T18:22:23.000Z","replies":[]},{"id":"Ugh_SFyObvI9UHgCoAEC","comment":"meetawada prasna tiyenawane lankawe meya presidda charitayak nisay hemotama prasne eka eyage kemettane neda ♡♡♡♡♡♡","author":"Thushara Sampath","likeCount":0,"totalReplyCount":0,"publishedAt":"2017-03-11T18:21:20.000Z","replies":[]},{"id":"Ugg8-XMcoVkijXgCoAEC","comment":"හොදයිනේ","author":"sameera ɮʀօ","likeCount":0,"totalReplyCount":0,"publishedAt":"2017-03-11T17:18:00.000Z","replies":[]},{"id":"UgiX385arn3jq3gCoAEC","comment":"anunge.dewal.hoyanne.mokatada.sinhalayage.bada.pirenne.anuge.kunu.hoyalama.","author":"buddika buddika","likeCount":2,"totalReplyCount":0,"publishedAt":"2017-03-11T17:02:45.000Z","replies":[]},{"id":"UghkbfqCIIZysHgCoAEC","comment":"oba depala hondata galapenawa. suba diwiyakata asiri...","author":"shyama Liyanage","likeCount":0,"totalReplyCount":0,"publishedAt":"2017-03-11T14:31:11.000Z","replies":[]},{"id":"UggXYf7_Qyb7P3gCoAEC","comment":"ඊට වඩා ලොකු ප්‍රස්න මේ රටේ තියෙන්නෙ..","author":"අරැණ Shan","likeCount":2,"totalReplyCount":0,"publishedAt":"2017-03-11T11:49:59.000Z","replies":[]},{"id":"UgiO7wuUdKA2aHgCoAEC","comment":"රැපවාහිනියේ පත්තර වල හෙන පොර ටොක්ස් දෙන්නේ සිංහලකම, ධර්මය රකින්නා,පිනට පහල වි මුගේ ඇතුල කුනු ගදගහනවා, සරම උස්සලා බලාපිය මුගේ සරධර්ම! මුගේ හෙලුව මුලු ලොවම දැනගත්තා ! ළමයිගේ වෙදනාව හරිම සදාරනයි, හැබැයි ගියෝත් ගියා අයේ එන්න එපා!! අවසානයේ ලංකිය ප්‍රසිද්ධ කියමන සනත වෙ! ලංකාවෙ කලාකරැවා හිගන්නා යන්නය!","author":"showman","likeCount":1,"totalReplyCount":1,"publishedAt":"2017-03-11T09:28:16.000Z","replies":[{"parentId":"UgiO7wuUdKA2aHgCoAEC","authorDisplayName":"Akash Rasanjana","replyComment":"a2z muge paka nadakin mun wage un sangeetha kaarayo unanee","publishedAt":"2017-03-14T09:22:52.000Z","likeCount":0}]},{"id":"Ugg0pK0raIMXGHgCoAEC","comment":"meyata 33??\nmeyata 60vithra athi wage","author":"dahami hansika","likeCount":0,"totalReplyCount":0,"publishedAt":"2017-03-11T08:45:57.000Z","replies":[]},{"id":"Ugjjq3y8_aMYJHgCoAEC","comment":"omg","author":"dananjani kulatunga","likeCount":1,"totalReplyCount":0,"publishedAt":"2017-03-11T05:27:34.000Z","replies":[]},{"id":"UgiJW_CPAsg6TngCoAEC","comment":"ඔයිට වඩා වෙනස් අයරටේ.කෝච්චර.සිටිද","author":"sudesh peryadarsahna","likeCount":2,"totalReplyCount":2,"publishedAt":"2017-03-11T03:36:44.000Z","replies":[{"parentId":"UgiJW_CPAsg6TngCoAEC","authorDisplayName":"Chandra Kumara","replyComment":"+chathuri chathuri hi","publishedAt":"2017-06-03T15:22:52.000Z","likeCount":0},{"parentId":"UgiJW_CPAsg6TngCoAEC","authorDisplayName":"chathuri chathuri","replyComment":"sudesh peryadarsahna hmmm","publishedAt":"2017-03-11T17:38:54.000Z","likeCount":0}]},{"id":"UggdcWo80-VLdHgCoAEC","comment":"75i 33nai dn ratema prashne wela thinne meka rate minissunta mewa penunata horu225k sapa vidinawa rata iwara karana gaman awa penne na waradda kauru karath waradi ekata me ratama masa ganak mekama katha kara kara inne mewage 5k awoth awruddak iwarai","author":"suneth malinga","likeCount":2,"totalReplyCount":0,"publishedAt":"2017-03-11T02:48:41.000Z","replies":[]},{"id":"Ugik-JY9nsk6IXgCoAEC","comment":"manussaya yam dawasaka tama weradi terum gena hedena dawasak eta.et me minissu kawadada hedenne.walapallata giyat hedeida.tamanta gelepena geniyek beda gattanam kamak na.matanam apilikul mewani minisun","author":"w ss wss","likeCount":0,"totalReplyCount":0,"publishedAt":"2017-03-11T02:40:45.000Z","replies":[]},{"id":"Ugg5rNRG2xp00HgCoAEC","comment":"naki vise getat usai.ara daru munupuran nalawanna tiyena kale.monada me mala kolam","author":"w ss wss","likeCount":0,"totalReplyCount":0,"publishedAt":"2017-03-11T02:37:27.000Z","replies":[]},{"id":"UgjUOwKNGGsFY3gCoAEC","comment":"anee appe apee senhalayata geya kalak.meeka nekam ara muslem menessu wageene.80  vetara muslem menessu 18 kello kasaada badenawa wagee.","author":"Ramya. Ramya.","likeCount":0,"totalReplyCount":0,"publishedAt":"2017-03-10T22:49:18.000Z","replies":[]},{"id":"Ugi5B88KH97FvHgCoAEC","comment":"ndaaaaken pakaya.keyanna wachana naa.mee kella mooda magulak","author":"Ramya. Ramya.","likeCount":0,"totalReplyCount":0,"publishedAt":"2017-03-10T22:45:27.000Z","replies":[]},{"id":"Ugjz-hX9ov55K3gCoAEC","comment":"Good to see him happy. good luck Victor.","author":"jetcrazy777","likeCount":0,"totalReplyCount":0,"publishedAt":"2017-03-10T22:20:46.000Z","replies":[]},{"id":"Ugjc5U0oxhYyp3gCoAEC","comment":"nodakin koti 100k danawa kiuwath hota bima anuna nakiyak akka matanam aka dawasak wath epa","author":"yashoodara h","likeCount":0,"totalReplyCount":0,"publishedAt":"2017-03-10T22:14:59.000Z","replies":[]},{"id":"Ugjl_pmO8WIKlXgCoAEC","comment":"nodakin me genu minissu ubalage gewal wala adu padu hadaganilla anunge ewata bena bena inne netiwa hari paththini ammalai upasaka thattalai inne me rate anunge kunu hoyanne lajja Nedda api nodanna ubalage wedagathkama","author":"pushpa wijerathne","likeCount":2,"totalReplyCount":1,"publishedAt":"2017-03-10T18:47:57.000Z","replies":[{"parentId":"Ugjl_pmO8WIKlXgCoAEC","authorDisplayName":"Shanuka Botheju","replyComment":"Pushpi kum Wijerathna respect sister we need more people like you it's nice to seen someone positive among thousands of negative people","publishedAt":"2017-03-11T08:00:52.000Z","likeCount":0}]},{"id":"UgiLBQTMvMm_F3gCoAEC","comment":"meki hithanawa athi sundari ......\n\n\n  kiyala  me ballita  wena miniyek\n hitiyema nadda","author":"Niroo Kumari","likeCount":0,"totalReplyCount":0,"publishedAt":"2017-03-10T18:37:27.000Z","replies":[]},{"id":"UghwA0vbMDtYLHgCoAEC","comment":"Makita 48 \/ 50 ka penumane","author":"Niroo Kumari","likeCount":0,"totalReplyCount":0,"publishedAt":"2017-03-10T18:34:27.000Z","replies":[]},{"id":"UghW9i-jTWYwBHgCoAEC","comment":"wayasai ganitath..monawa unath...sathutin innawanam kauru hari aka apath sathuta","author":"Lirisha Kumari","likeCount":0,"totalReplyCount":0,"publishedAt":"2017-03-10T17:51:28.000Z","replies":[]},{"id":"Ugi7o_stwZtknHgCoAEC","comment":"ane manda mama nam mehema viwahayak gana ahuwamai me lankawe.hammeee sansaleee he heee meyata habai 33 wada nam wadi wage.kohoama namuth apenuth suba pathum jaya siri mangalam.","author":"chathurika seuwandi","likeCount":0,"totalReplyCount":0,"publishedAt":"2017-03-10T16:47:34.000Z","replies":[]},{"id":"UggPz5lFQugUJngCoAEC","comment":"lassanai.","author":"nirosha vijesingha","likeCount":0,"totalReplyCount":0,"publishedAt":"2017-03-10T15:35:18.000Z","replies":[]},{"id":"Ughm1ZlPbhoKdHgCoAEC","comment":"oki lamayakuta dipan victor","author":"Smart Tharindu","likeCount":0,"totalReplyCount":0,"publishedAt":"2017-03-10T15:26:00.000Z","replies":[]},{"id":"Ugh0rQjbaZudvHgCoAEC","comment":"rate katawa me gana witharai meyata wada kocchara thiyeda","author":"Tiki Tikireme","likeCount":1,"totalReplyCount":0,"publishedAt":"2017-03-10T14:54:22.000Z","replies":[]},{"id":"Ugh3u8SPZntr6ngCoAEC","comment":"jealousy & hypocrisy..","author":"Sweeny Fernando","likeCount":0,"totalReplyCount":1,"publishedAt":"2017-03-10T14:00:16.000Z","replies":[{"parentId":"Ugh3u8SPZntr6ngCoAEC","authorDisplayName":"Sanjeevanee Silva","replyComment":"ඵකඵයාගේ කැමැත්ත මීටවාඩා දේවල්අප්රටේ තියෙනවානේ ඵමනූස්යාට අපාසකරලා මේඅයමෝන වදබලාපොරුතු  වන්නේ","publishedAt":"2017-03-14T03:44:56.000Z","likeCount":0}]},{"id":"Ugj6MrPtHJ8f23gCoAEC","comment":"Victor Ratnayake kawadawath hinawela godak santhoshayen katha krana knek nowe. Bohoma tharaha adambararayakin uthu charithayak kiyai  ma sithuwe. May video eke dakka  sinahawa pitipasa  sitinne  ohuge deweni manamaliya nam e  gaurawa  ayata himiwiya uthui. kisi kenek dukbarawa thanikadawa miya ya uthu naha. Kohoma jivath unath minissu katha hadana eka walakwanna baha. Mama Victor Ratnayake kalakaruwa paudgalikawa hadunana kenek nowe, aurudu gaanakata pera prasangayakadi ohu samaga chayarrupayakata peni sitiya. Dharuwo sitiyata ada kiyen kee denada demaupiyawa balaganne? Ada hama denama awiweki  jeevitha gatha kranne, Arthika prasna nisa demaupiyanwa magaharenawa, swaminwahansela mona bana keuwath ada arthikaya sama prasnayakatama mul wela, minissu amanussayan wela salli hoyagenama duwanawa. Lamainge jeevitha tution panthi wala. Wayasaka demaipiyan gedara kotu wela, thani wela., katha kranna knek nathuwa.\n Demapiyan daruwanta yatathwa jeewath viya uthu naha  mehema hari katawath karadarayak nowi jeevath wenna puluwannam!  Mohuta jeevath wanna mudal thiyenawa, ithin balaganna biridak gathtata eke thiyena warada mkakda?  May vivahaya arthika vasi walin thora  sathya premaya pera darikota unu siduweemk nam ape subha pathum!","author":"indigo franka","likeCount":1,"totalReplyCount":1,"publishedAt":"2017-03-10T13:14:39.000Z","replies":[{"parentId":"Ugj6MrPtHJ8f23gCoAEC","authorDisplayName":"indigo franka","replyComment":"wadakaara kamata hari awilla inne kamaththen neda, ehema  nam badinna oneth naha neda, puluwan nam bahutharayak oya dema karawi, bari aya katha hadawi.","publishedAt":"2017-03-17T09:50:37.000Z","likeCount":0}]},{"id":"UgiMT3BsTAQ-vHgCoAEC","comment":"Mona sangeetha kaarayek unath wedak neha.\n Mey naaki miniha ara amma nethi duruwo hathara denaata samaajayata muhuna denna idak thibbe neha. minissu naaki wenne idoretada. manussakam danne nedda.\n\n  piyawaru mehemada.\n\nwili  lejjaawa daruwanta.","author":"Mallika Mallika","likeCount":0,"totalReplyCount":0,"publishedAt":"2017-03-10T12:59:25.000Z","replies":[]},{"id":"Uggm2poAiB-Xv3gCoAEC","comment":"ada kala gani daruwo jiwath wela inne kotath wene ganu ekka dige kane pirimi inne meke nam pasneyak nemei mokoda nona nathiwela nisha eya wene viwahayak kara gaththata waradak na man nam hada wethinma suba pathanewaa ...","author":"dinusha","likeCount":1,"totalReplyCount":0,"publishedAt":"2017-03-10T12:37:41.000Z","replies":[]},{"id":"UgjA7bOqjac-vngCoAEC","comment":"දරුවො තාත්තා ගන බලයිද ගනිට දරුවො ලොකු උනාම","author":"Fathima Rinoza","likeCount":0,"totalReplyCount":2,"publishedAt":"2017-03-10T12:25:50.000Z","replies":[{"parentId":"UgjA7bOqjac-vngCoAEC","authorDisplayName":"Fathima Rinoza","replyComment":"mohamed shiyam ..anna nigaluma ada ketinga unma thane pullayal mudicha poraw thai thwpana pakaraya sri lankawala මහලු madam ikire ada nala thane","publishedAt":"2017-03-11T17:14:18.000Z","likeCount":0},{"parentId":"UgjA7bOqjac-vngCoAEC","authorDisplayName":"shiyam시얌","replyComment":"Fathima Rinoza neengaluma?","publishedAt":"2017-03-11T15:57:00.000Z","likeCount":0}]},{"id":"Ugge_a8vUMEmVXgCoAEC","comment":"pem rasa wahena mangala gethe gevitheeeee.👍👍👍👍👍💕💕💕","author":"rhadikak rhadikak","likeCount":0,"totalReplyCount":0,"publishedAt":"2017-03-10T11:53:00.000Z","replies":[]},{"id":"UgiGgdvbX04y5ngCoAEC","comment":"e ganita 33 nam kage hari plane ekak ekko charichaya ghatanayata natnam daruvange aitiya uduraganiimata natnam adareeta nevei samahara vita ganikaavak venna ati","author":"sena qatar","likeCount":0,"totalReplyCount":0,"publishedAt":"2017-03-10T11:42:04.000Z","replies":[]},{"id":"UghCbpZtOZzvdngCoAEC","comment":"kaage kamatta unat daruvange atma garuttvaya kelasapu vadagat tatta kenek.antimata predee silva mahathata vechcha dee venava niyatai.atta katavaknam.antimata kisi kenek salakanne naa.antimata paree marila yanava.passe daruvange varadda kiyanava","author":"sena qatar","likeCount":0,"totalReplyCount":0,"publishedAt":"2017-03-10T11:40:21.000Z","replies":[]},{"id":"UgiN_lfJg6InpXgCoAEC","comment":"victor ,I appreciate  you, man has no age,we,ourselves count age,no age, no time,nothing in this world,we have been deceived our ancestors, l wish you happy marriage, and happy life,l also wish your wife","author":"Nihal Dissanayake","likeCount":0,"totalReplyCount":0,"publishedAt":"2017-03-10T11:17:56.000Z","replies":[]},{"id":"UggReXvr3TwgAngCoAEC","comment":"ඵ්ක Dr. VR ගෙ අයිතිය..ඉතින් අපිට මොකෝ..දෙලොවටම නොවැදගත්  ඔිපදුප සොයන,කතා කරන මිනුස්සු ඉන්නෙ ලංකාවෙ පමණි..\nඑනිසා  ලංකාව, තුන්වන ලෝකයේ දියුණු නොකල හැකි රටකි....","author":"Ridwan Roshan","likeCount":2,"totalReplyCount":2,"publishedAt":"2017-03-10T10:58:18.000Z","replies":[{"parentId":"UggReXvr3TwgAngCoAEC","authorDisplayName":"veranga kumara","replyComment":"maim hsthum","publishedAt":"2019-08-12T12:30:10.000Z","likeCount":0},{"parentId":"UggReXvr3TwgAngCoAEC","authorDisplayName":"ruveena Thushari","replyComment":"patta aththa affa.","publishedAt":"2017-03-10T11:31:48.000Z","likeCount":0}]},{"id":"UgjKQJLRFkl59HgCoAEC","comment":"aeka aeyage kamahtta","author":"LIAR LIAR","likeCount":0,"totalReplyCount":0,"publishedAt":"2017-03-10T10:17:41.000Z","replies":[]},{"id":"UgihlsZ8TKudlngCoAEC","comment":"nodakin  tamangi daruwongi  wayasi nida gani munta ලජ්ජාවක්  nati kama tirisannu wagi hasirinna epa budun 2 rk wadiya api rata nida meka","author":"Rika Dilrukshi","likeCount":0,"totalReplyCount":0,"publishedAt":"2017-03-10T09:59:48.000Z","replies":[]},{"id":"UgiNTrXJwdpLjHgCoAEC","comment":"mewa maha loku dewal newei.","author":"Dewanga Jayaweera","likeCount":0,"totalReplyCount":0,"publishedAt":"2017-03-10T09:56:32.000Z","replies":[]},{"id":"UghEF6kvNA31w3gCoAEC","comment":"mewa maha loku dewal newei.","author":"Dewanga Jayaweera","likeCount":0,"totalReplyCount":0,"publishedAt":"2017-03-10T09:56:22.000Z","replies":[]},{"id":"UgjByZv3_lMEi3gCoAEC","comment":"අපි හැමදාමත් ආදරේ කරේ ඔහුගේ ගායනයට ඔහුගේ ගිතවලට..දෙවෙනි විවාහයක් කරගත්ත එක ඔහුගේ කැමැත්ත...අපි හැමදාමත් රස විදින්නේ වික්ටරත්නායකයානන්ගේ ගිත මිස..ඔහුගේ පුද්ගලික ජිවිතය නොවේ..","author":"anu anu","likeCount":1,"totalReplyCount":0,"publishedAt":"2017-03-10T09:51:18.000Z","replies":[]},{"id":"UgiobPul-4TqingCoAEC","comment":"අපි හැමදාමත් ආදරේ කරේ ඔහුගේ ගායනයට ඔහුගේ ගිතවලට..දෙවෙනි විවාහයක් කරගත්ත එක ඔහුගේ කැමැත්ත...අපි හැමදාමත් රස විදින්නේ වික්ටරත්නායකයානන්ගේ ගිත මිස..ඔහුගේ පුද්ගලික ජිවිතය නොවේ.","author":"anu anu","likeCount":3,"totalReplyCount":0,"publishedAt":"2017-03-10T09:51:09.000Z","replies":[]},{"id":"UggNlMye5DKoe3gCoAEC","comment":"😂😂 owa rattu hinassana weda ponnayooo","author":"lk swagger","likeCount":7,"totalReplyCount":8,"publishedAt":"2017-03-10T09:49:59.000Z","replies":[{"parentId":"UggNlMye5DKoe3gCoAEC","authorDisplayName":"Tushari K.A.","replyComment":"lk swagger rattu hinassana weda thamuse dakala ne.umbalage gedara thiyena kunu sudda karaganin ban","publishedAt":"2017-06-10T20:01:22.000Z","likeCount":0},{"parentId":"UggNlMye5DKoe3gCoAEC","authorDisplayName":"Tushari K.A.","replyComment":"lk swagger ponnaya umbai.gihin mal mal chiithayak thanpota gahan pala game linda gawata.eeka nambuibanunge magul walata kenahilikam karanawata wada.","publishedAt":"2017-06-10T20:00:29.000Z","likeCount":0},{"parentId":"UggNlMye5DKoe3gCoAEC","authorDisplayName":"Tushari K.A.","replyComment":"muu gedarata naki wena ekekda koheda eekai me victor wayasata gihillath tharuniyak wiwaha unata thiyena tharaha.ponnayek nam kohendo buruwo ara daruwo? thoge thattageda?","publishedAt":"2017-06-10T19:57:16.000Z","likeCount":0},{"parentId":"UggNlMye5DKoe3gCoAEC","authorDisplayName":"lk swagger","replyComment":"thamange duwage wayase genu set karanna eka ponna kamak ne bola huthooo 😂😂😂 chatara oiiii wessa genuuu","publishedAt":"2017-03-13T07:28:25.000Z","likeCount":2},{"parentId":"UggNlMye5DKoe3gCoAEC","authorDisplayName":"Lilindu Dasun","replyComment":"kawda huththo ponnaya?kellek set karaganna bari thopi thamai ponnayo","publishedAt":"2017-03-13T02:28:20.000Z","likeCount":2},{"parentId":"UggNlMye5DKoe3gCoAEC","authorDisplayName":"Lilindu Dasun","replyComment":"kawda huththo ponnaya?kellek set karaganna bari thopi thamai ponnayo","publishedAt":"2017-03-13T02:28:06.000Z","likeCount":1},{"parentId":"UggNlMye5DKoe3gCoAEC","authorDisplayName":"Lilindu Dasun","replyComment":"kawda huththo ponnaya?kellek set karaganna bari thopi thamai ponnayo","publishedAt":"2017-03-13T02:27:59.000Z","likeCount":1},{"parentId":"UggNlMye5DKoe3gCoAEC","authorDisplayName":"sarasarajung","replyComment":"lk swagger ponnayo gaanu gannawada bang?","publishedAt":"2017-03-11T09:46:20.000Z","likeCount":4}]},{"id":"UgiUGt1NyytLRHgCoAEC","comment":"wittar rathnayakata aurudu75 .meyage aluth nonage thaththata aurudu 73 lu kohomada wenasa.","author":"Sarath Vijesinghe","likeCount":0,"totalReplyCount":0,"publishedAt":"2017-03-10T09:41:35.000Z","replies":[]},{"id":"Ugg_uK20akqR4HgCoAEC","comment":"gahanu kenata hoyaganna tharunayek idala naha.ekawennaathi karane","author":"صباء اهل","likeCount":0,"totalReplyCount":0,"publishedAt":"2017-03-10T09:29:45.000Z","replies":[]},{"id":"UghrtlFRh-1cT3gCoAEC","comment":"daruwo aei key gahanne.aeyala kiyanne me genu kena hodane kiyalaneda .ane manda.apita mokada..aeyage kemeththane.","author":"D.k.malwattha. Kumari","likeCount":0,"totalReplyCount":0,"publishedAt":"2017-03-10T09:25:56.000Z","replies":[]},{"id":"Ugi_fM-jvJgqwHgCoAEC","comment":"මොනව උනත් මං සුබපතනව වික්ටර් සර්ට","author":"niroshani suriya","likeCount":1,"totalReplyCount":0,"publishedAt":"2017-03-10T09:21:19.000Z","replies":[]},{"id":"UggkOB0WvxuCDXgCoAEC","comment":"me rate ewun bahutharayak anunnge de wal thami  hoyanne .thamanta mona tharam karadara edda.ewata uththara hoyanne ne.kalakanni minissu kotasak .","author":"krishanthamohan perera","likeCount":9,"totalReplyCount":4,"publishedAt":"2017-03-10T09:08:24.000Z","replies":[{"parentId":"UggkOB0WvxuCDXgCoAEC","authorDisplayName":"aysha riyas riyasaysha","replyComment":"krishanthamohan perera ekanam attha","publishedAt":"2017-03-11T18:43:33.000Z","likeCount":0},{"parentId":"UggkOB0WvxuCDXgCoAEC","authorDisplayName":"Hemantha sisira kumara Jhs","replyComment":"krishanthamohan perera  aniwaren","publishedAt":"2017-03-11T00:16:13.000Z","likeCount":0},{"parentId":"UggkOB0WvxuCDXgCoAEC","authorDisplayName":"R.S.Shaya Udayangani degree in journalism","replyComment":"krishanthamohan perera aththa apitanam anunge dewal wedakma ne.","publishedAt":"2017-03-10T16:53:43.000Z","likeCount":1},{"parentId":"UggkOB0WvxuCDXgCoAEC","authorDisplayName":"ruveena Thushari","replyComment":"meke comnts kiwwama pissu hedenawa affa.janapriya kenek nisaneda me.samanya kenek 80n 20 kellek bendath hoyaida minissu a gena.hari kuhaka samajayak neh..tika kalekin thaththala puthala,punchammala  samadana wela hodin idiwi.edata dana photo walatath minissu baniwi.ai minissu mehema affa..","publishedAt":"2017-03-10T11:42:17.000Z","likeCount":3}]},{"id":"UggfEWzH58xcY3gCoAEC","comment":"ara daruwanta labenna thibinu dewal me kapati paratti aithi kara gathth wiktar ta nemei meki kamathi a manusayage salli walata rate wena minisu nathuwada mekige siya wage me manusaya oba thumage budale serama lamainta dila meki gawata yanna ko bara ganida kiyala balanna meka mage adahasak pamanai winter rathina yakayange hada sada nomiyana hadaki","author":"ROSHAN SURANGI","likeCount":0,"totalReplyCount":0,"publishedAt":"2017-03-10T08:55:16.000Z","replies":[]},{"id":"Ugi0OieD10FK33gCoAEC","comment":"All the best","author":"R Gun","likeCount":0,"totalReplyCount":1,"publishedAt":"2017-03-10T08:30:41.000Z","replies":[{"parentId":"Ugi0OieD10FK33gCoAEC","authorDisplayName":"Richard Perera","replyComment":"ros\n\nhan gunathilake","publishedAt":"2017-03-11T07:36:48.000Z","likeCount":0}]},{"id":"UgjftP2MTy3ofXgCoAEC","comment":"muna baluwama penawa hoda ammandiyek kiyala...","author":"Kisal Samaranayake","likeCount":0,"totalReplyCount":0,"publishedAt":"2017-03-10T08:25:26.000Z","replies":[]},{"id":"UgjDDRL9NE4-lHgCoAEC","comment":"hukana vidiyo danna epa huththo meke e ganu kena bahane ethana inne viktar rathnayakage duwa thopita hena gahanawa muwage boru danawata nodakin musalaya","author":"Nalin Sl","likeCount":2,"totalReplyCount":4,"publishedAt":"2017-03-10T08:23:34.000Z","replies":[{"parentId":"UgjDDRL9NE4-lHgCoAEC","authorDisplayName":"chathuri chathuri","replyComment":"Nalin Sl ana oya kiyana da attaknam munta hana gahanna oni paw wada karanawata 😐😐😐","publishedAt":"2017-03-11T17:37:54.000Z","likeCount":0},{"parentId":"UgjDDRL9NE4-lHgCoAEC","authorDisplayName":"Damayanthi rajapakshe Rajapakshe","replyComment":"Kanishka Rox good joke😂😂😂","publishedAt":"2017-03-10T15:31:27.000Z","likeCount":2},{"parentId":"UgjDDRL9NE4-lHgCoAEC","authorDisplayName":"Sweeny Fernando","replyComment":"omg","publishedAt":"2017-03-10T14:08:29.000Z","likeCount":2},{"parentId":"UgjDDRL9NE4-lHgCoAEC","authorDisplayName":"අැම්,පි,ලිලාරත්න ගමගේ","replyComment":"සිත නිවන කතා","publishedAt":"2017-03-10T09:55:02.000Z","likeCount":0}]},{"id":"Ugg33MZnYTMXh3gCoAEC","comment":"aka ayalage kamattha anunge waradi hoyanawata wada narakada thamange waradi hoyagatthanam thawa kenekta agilla dik karanakota thamanta agili 3k ma namila hamoma aheama hithanawanam apea ratea opa dupa aduyii","author":"Anu Anu godak lassanayii","likeCount":4,"totalReplyCount":1,"publishedAt":"2017-03-10T08:06:56.000Z","replies":[{"parentId":"Ugg33MZnYTMXh3gCoAEC","authorDisplayName":"Aki Vip","replyComment":"ekenma hada","publishedAt":"2017-03-10T09:30:32.000Z","likeCount":2}]},{"id":"UghMTuf9zTWh4XgCoAEC","comment":"minissunta mada gahanda apa yako....thopita hena gahanawa.anunta akeke kiyanda kalin....thamnge gedara tiyana awa tikak balapalla....","author":"Mithu Dil","likeCount":2,"totalReplyCount":1,"publishedAt":"2017-03-10T07:58:38.000Z","replies":[{"parentId":"UghMTuf9zTWh4XgCoAEC","authorDisplayName":"Aki Vip","replyComment":"ekenma hada","publishedAt":"2017-03-10T09:31:00.000Z","likeCount":0}]},{"id":"UghLVmm_J4J1zngCoAEC","comment":"60 pannath moko","author":"ishara karunarathna","likeCount":1,"totalReplyCount":0,"publishedAt":"2017-03-10T07:55:15.000Z","replies":[]},{"id":"UggYMnd5CHtJc3gCoAEC","comment":"me kurunegala da","author":"Heshan Thilakarathna","likeCount":2,"totalReplyCount":1,"publishedAt":"2017-03-10T06:11:23.000Z","replies":[{"parentId":"UggYMnd5CHtJc3gCoAEC","authorDisplayName":"Rasaduna රසදුන","replyComment":"yes..","publishedAt":"2017-03-10T06:12:41.000Z","likeCount":3}]},{"id":"UgiteaO9ZahilHgCoAEC","comment":"Ane manda....  kamak neha ithin ethumata handa nam apata moko  LOL","author":"nukestrom","likeCount":2,"totalReplyCount":0,"publishedAt":"2017-03-10T05:33:17.000Z","replies":[]},{"id":"UgjRXio17u-XZngCoAEC","comment":"එකෙක් beinam 10k බැන්ද t අපිට මොකද","author":"Lakshika Sham","likeCount":3,"totalReplyCount":0,"publishedAt":"2017-03-10T04:51:08.000Z","replies":[]},{"id":"UgjI0BmiaMG5kXgCoAEC","comment":"beautiful !!!  goodhealth & happiness !!.","author":"Sweeny Fernando","likeCount":0,"totalReplyCount":0,"publishedAt":"2017-03-10T04:45:05.000Z","replies":[]},{"id":"Ugikow3oDGKByngCoAEC","comment":"eka eththa. me genu kenata ita wada wayasa ethi..33 ta den kale inne podi girlsla. kohoma unath suba pethum.","author":"Usha P","likeCount":1,"totalReplyCount":0,"publishedAt":"2017-03-10T04:44:49.000Z","replies":[]},{"id":"Ugiv6v0zBNnX2XgCoAEC","comment":"theruwan saranayi oba depalata suba mangalam","author":"Sandun De Zoysa","likeCount":5,"totalReplyCount":1,"publishedAt":"2017-03-10T04:14:13.000Z","replies":[{"parentId":"Ugiv6v0zBNnX2XgCoAEC","authorDisplayName":"Amali Sudu","replyComment":"suba mangalam.budusaranae.","publishedAt":"2017-03-10T11:14:54.000Z","likeCount":3}]},{"id":"UggBrAHAzRgM43gCoAEC","comment":"NAKI WISE GETATH USE","author":"sherin fernando","likeCount":6,"totalReplyCount":2,"publishedAt":"2017-03-10T02:44:27.000Z","replies":[{"parentId":"UggBrAHAzRgM43gCoAEC","authorDisplayName":"Softlink Spc","replyComment":"sherin fernan\n\ndo","publishedAt":"2017-08-19T03:19:51.000Z","likeCount":0},{"parentId":"UggBrAHAzRgM43gCoAEC","authorDisplayName":"Aki Vip","replyComment":"ohe nakiwenne nane hada","publishedAt":"2017-03-10T09:32:23.000Z","likeCount":2}]},{"id":"UggR7-0ZYQOKbHgCoAEC","comment":"good luck. victor  mahathmaya.","author":"rashi Imesh","likeCount":0,"totalReplyCount":0,"publishedAt":"2017-03-10T01:05:10.000Z","replies":[]},{"id":"Ugg4ufbiXQFRiHgCoAEC","comment":"meka mokakda. mewa magic wage penne wadak karanne nathuwa kaka bibi gewal walata wela inna. ganu  minissunta.","author":"rashi Imesh","likeCount":5,"totalReplyCount":1,"publishedAt":"2017-03-10T01:04:04.000Z","replies":[{"parentId":"Ugg4ufbiXQFRiHgCoAEC","authorDisplayName":"Aki Vip","replyComment":"atta me aperate minissu ganunta tele tamunge kunu perenawa anunge kunut hoyanawa ane kale wane wase","publishedAt":"2017-03-10T09:33:48.000Z","likeCount":3}]},{"id":"UggVW52SjTkS0XgCoAEC","comment":"sir budu saranai oyata..all the best you and your wife..","author":"Nuwan Shamali","likeCount":1,"totalReplyCount":0,"publishedAt":"2017-03-10T00:25:46.000Z","replies":[]},{"id":"UggjQQTqtf7t13gCoAEC","comment":"how ironic, So the wedding photos are censored to allow the bride and groom their privacy, yet, I guess this couple don't deserve it because, ooh, they have an age gap? \noh the absolute horror!!  How dare they! it's not like any one ever has seen a couple with an age gap before!!!!\nGrow up people! This is a common occurrence! Geez!","author":"Thil","likeCount":1,"totalReplyCount":0,"publishedAt":"2017-03-10T00:08:32.000Z","replies":[]},{"id":"UggekVZsGEClY3gCoAEC","comment":"nathuwata mala kolan \nrattu hinassanawa\ndaruwanta th lajjai","author":"kusum Wickrama archchi","likeCount":0,"totalReplyCount":0,"publishedAt":"2017-03-10T00:00:32.000Z","replies":[]},{"id":"UgiQufNyhDSQOXgCoAEC","comment":"Viktor mahaththayage, Deweni upatha ho... ekko, awasanayai mea....","author":"Lanka Land & Kandy Property","likeCount":1,"totalReplyCount":0,"publishedAt":"2017-03-09T23:19:31.000Z","replies":[]},{"id":"UgjDQkJspOd6P3gCoAEC","comment":"theruwan saranayi oba depalata suba mangalam","author":"malki malki","likeCount":1,"totalReplyCount":0,"publishedAt":"2017-03-09T23:14:18.000Z","replies":[]},{"id":"UggH5QxA_YSO73gCoAEC","comment":"ඒ දෙන්න කැමැති.නිසානෙ එයාල කරගත්තෙ කවුරැවත් ඒක පුශ්නයක් කරගන්න එපා ඹබ දෙපලට  සුභ මංගලමි","author":"Sonita Sonita","likeCount":6,"totalReplyCount":1,"publishedAt":"2017-03-09T22:20:19.000Z","replies":[{"parentId":"UggH5QxA_YSO73gCoAEC","authorDisplayName":"asoka ratnayake","replyComment":"oyath yanna","publishedAt":"2018-03-24T12:21:59.000Z","likeCount":0}]},{"id":"UghEwnQ4Wrxgs3gCoAEC","comment":"keri sayanna oya... Thani tharuwe...pala pakaya borukiyannetiva.","author":"jayasuriya jayasiri","likeCount":0,"totalReplyCount":0,"publishedAt":"2017-03-09T22:15:44.000Z","replies":[]},{"id":"UghvZoVo2PpagngCoAEC","comment":"Hadai budu saranai dannathama","author":"dil hani","likeCount":1,"totalReplyCount":0,"publishedAt":"2017-03-09T22:08:08.000Z","replies":[]},{"id":"Ugh_0zE7MjBYy3gCoAEC","comment":"33nam wedi eth thatthai duwai wage....mewa naki kolan.","author":"Nethu ekanayaka","likeCount":0,"totalReplyCount":2,"publishedAt":"2017-03-09T21:49:38.000Z","replies":[{"parentId":"Ugh_0zE7MjBYy3gCoAEC","authorDisplayName":"Nethu ekanayaka","replyComment":"Aki Vip 😆😆😆😆😆😆","publishedAt":"2017-03-10T09:36:27.000Z","likeCount":0},{"parentId":"Ugh_0zE7MjBYy3gCoAEC","authorDisplayName":"Aki Vip","replyComment":"irisiya karanna epa broo","publishedAt":"2017-03-10T09:35:22.000Z","likeCount":0}]},{"id":"Ugg7cAvM9SWSG3gCoAEC","comment":"hari lajjayi.reason why?1st he married man.age is now 75.so why get a married again.???.","author":"Ridley Suranjith","likeCount":0,"totalReplyCount":1,"publishedAt":"2017-03-09T21:07:37.000Z","replies":[{"parentId":"Ugg7cAvM9SWSG3gCoAEC","authorDisplayName":"ruveena Thushari","replyComment":"he deserves to be happy that's what I think and the other thing is personal matter.","publishedAt":"2017-03-10T11:24:49.000Z","likeCount":0}]},{"id":"UghoJCWiYYggw3gCoAEC","comment":"suba pethum...budu saranai oba dealata","author":"Priyangika Niroshini","likeCount":3,"totalReplyCount":0,"publishedAt":"2017-03-09T20:24:34.000Z","replies":[]},{"id":"UgibE5MDoYOVAngCoAEC","comment":"එක එයාගෙ කැමත්ත එක ඉතින් ලොකු දෙයක් නෙමෙයි","author":"aisha vijayadas","likeCount":10,"totalReplyCount":1,"publishedAt":"2017-03-09T20:05:53.000Z","replies":[{"parentId":"UgibE5MDoYOVAngCoAEC","authorDisplayName":"Aki Vip","replyComment":"ok eiyal","publishedAt":"2017-03-10T09:35:43.000Z","likeCount":1}]},{"id":"UggfddtJ7Ym2VHgCoAEC","comment":"අමිමපා මාත් හෙටම කපනවා වික්ටර් කටි එක ඇන්ටි පාරක් සෙටි කරගන්ට 😂🔫","author":"Mahesh","likeCount":1,"totalReplyCount":1,"publishedAt":"2017-03-09T19:47:01.000Z","replies":[{"parentId":"UggfddtJ7Ym2VHgCoAEC","authorDisplayName":"pradeepa udayangani dubai sarja","replyComment":"සිංහළේ ...","publishedAt":"2017-03-10T14:56:34.000Z","likeCount":0}]},{"id":"UghyrXM1uCkzYHgCoAEC","comment":"hitagena innath bahe...dane ithin premayen math wela inne.nakiwise.....","author":"Dinnlenn Obyocas","likeCount":0,"totalReplyCount":0,"publishedAt":"2017-03-09T19:42:01.000Z","replies":[]},{"id":"Ugg8ZBRl3xE1CXgCoAEC","comment":"appada bola maru 33 kalla","author":"සද හැංගිලා","likeCount":1,"totalReplyCount":0,"publishedAt":"2017-03-09T19:39:15.000Z","replies":[]},{"id":"UgjsYlvpyAfqIXgCoAEC","comment":"suba mangalam  theruwansaranaii","author":"nodakg chang","likeCount":0,"totalReplyCount":0,"publishedAt":"2017-03-09T19:16:47.000Z","replies":[]},{"id":"UgiHUd3_j--BTXgCoAEC","comment":"daruwo kochchara hitiyath wayasata giyama ledak dukak hari kiyanna pirimiyekuta gahaniyak inna oni paw apinam subapathanawa","author":"තෙරුවන් සරණයි තෙරුවන් සරණයි","likeCount":30,"totalReplyCount":9,"publishedAt":"2017-03-09T19:02:01.000Z","replies":[{"parentId":"UgiHUd3_j--BTXgCoAEC","authorDisplayName":"Piyal Modara","replyComment":"e.s. A.l awankama","publishedAt":"2017-03-14T22:58:35.000Z","likeCount":0},{"parentId":"UgiHUd3_j--BTXgCoAEC","authorDisplayName":"Thamara Kumari Abeykoon","replyComment":"e.s. A.l ane mea oya gani salakaida  wayasata giyama daruwo thamai bana bana hari salakanne","publishedAt":"2017-03-14T22:06:48.000Z","likeCount":0},{"parentId":"UgiHUd3_j--BTXgCoAEC","authorDisplayName":"Ravi Indunil","replyComment":"nangi hari nangi","publishedAt":"2017-03-13T22:19:56.000Z","likeCount":1},{"parentId":"UgiHUd3_j--BTXgCoAEC","authorDisplayName":"layaback","replyComment":"ea kiyanne me ran thiyane wadakaara gAanu kenekdha?","publishedAt":"2017-03-13T04:08:13.000Z","likeCount":0},{"parentId":"UgiHUd3_j--BTXgCoAEC","authorDisplayName":"Sweeny Fernando","replyComment":"e s a.l  you are great !!.","publishedAt":"2017-03-11T09:53:57.000Z","likeCount":1},{"parentId":"UgiHUd3_j--BTXgCoAEC","authorDisplayName":"Mahesha Nelawala2","replyComment":"indigo franka wayasata hamoma yanawa ehema neme samahara daruwo demapiyanta salakanne naa eth  wayasata giyath godak adaren inna minissu nadda ledata dukata laga inna ekata gahanu pirimi wenasak na needa daruwo salakuwe natath koi taram ammala thatthala innawada wayasata giyath adaren inna mona duka hari widagana","publishedAt":"2017-03-10T13:27:01.000Z","likeCount":2},{"parentId":"UgiHUd3_j--BTXgCoAEC","authorDisplayName":"indigo franka","replyComment":"ai gahanu wayasata yanne nadda?","publishedAt":"2017-03-10T13:16:24.000Z","likeCount":2},{"parentId":"UgiHUd3_j--BTXgCoAEC","authorDisplayName":"Mahesha Nelawala2","replyComment":"eka attha","publishedAt":"2017-03-10T11:19:46.000Z","likeCount":0},{"parentId":"UgiHUd3_j--BTXgCoAEC","authorDisplayName":"Chanu Kqt","replyComment":"akanam hariyatama hari","publishedAt":"2017-03-10T06:35:32.000Z","likeCount":0}]},{"id":"Ugg6uPmyn_MdmXgCoAEC","comment":"33 පුක තමයි නකි මගුලක් ...මොඩයි අහු උනා අපේ සර්","author":"Nadeera Sadaruwan","likeCount":1,"totalReplyCount":0,"publishedAt":"2017-03-09T18:59:23.000Z","replies":[]},{"id":"UgjxnQVKG4nF8HgCoAEC","comment":"adaidala muge sindu ahanneth ne mama","author":"Pancha Promodya","likeCount":0,"totalReplyCount":0,"publishedAt":"2017-03-09T18:48:18.000Z","replies":[]},{"id":"UghZEO1uTUTXYHgCoAEC","comment":"pinak dahamak karan.innaona.kale.muta.genugana mathkwela tiyenne.minipiri Saha.siya a ekai aeththa","author":"Pancha Promodya","likeCount":7,"totalReplyCount":2,"publishedAt":"2017-03-09T18:45:30.000Z","replies":[{"parentId":"UghZEO1uTUTXYHgCoAEC","authorDisplayName":"sarasarajung","replyComment":"Pancha Promodya ලේ නෑකමක් නැතුව මිනිපිරි වෙන්නෙ කොහොමද? owa nikan gon katha. gaaniyeknan pirimiyeknan echcharai. thibiya yuthu vayasa paratharaya kiyanne nikan minissu hada gaththa deyak. seeyage vayase unata seeya nemeine. ethakota ayyage vayase minihek bandoth thamage ayya venawada.","publishedAt":"2017-03-11T09:57:25.000Z","likeCount":0},{"parentId":"UghZEO1uTUTXYHgCoAEC","authorDisplayName":"පුන්චි හිතුවක්කාරයා","replyComment":"Pancha Promodya අපට මොකෝ හලෝ  අපි කන්ද උදට නගින්නෙ ලෝකෙට අපිව පේන්න නෙවෙයිනේ  අපි ලෝකෙ දිහා බලන්න නේ  ඒ දෙන්නගෙ පාඩුවේ එයාල ගමන යනවා අපටයි රිදෙන්නේ","publishedAt":"2017-03-09T20:33:08.000Z","likeCount":19}]},{"id":"UghzvWGL2f09xngCoAEC","comment":"සුභ මංගලම් .!!!    ඔබ   දෙපලට  වාසනා වන්ත  යුග  දිවියකට  සුභ පැතුම්..","author":"Rita Srilanka","likeCount":0,"totalReplyCount":0,"publishedAt":"2017-03-09T18:36:55.000Z","replies":[]},{"id":"UgiP1GNE6jy-8XgCoAEC","comment":"aiyoooooo.naki.visa","author":"cmk pnm","likeCount":2,"totalReplyCount":0,"publishedAt":"2017-03-09T18:01:47.000Z","replies":[]},{"id":"UggqKzDJOMJnAngCoAEC","comment":"maara lucky viktar aiyaa nam...","author":"Renuka Silva","likeCount":0,"totalReplyCount":0,"publishedAt":"2017-03-09T18:00:46.000Z","replies":[]},{"id":"UgiwK4gIQGae-3gCoAEC","comment":"edithara gahaniyak...","author":"Renuka Silva","likeCount":0,"totalReplyCount":0,"publishedAt":"2017-03-09T17:56:32.000Z","replies":[]},{"id":"UgiK09jUY0OorngCoAEC","comment":"hora duushana walata wadadaa nam good...","author":"Renuka Silva","likeCount":1,"totalReplyCount":0,"publishedAt":"2017-03-09T17:52:33.000Z","replies":[]},{"id":"Ugg6Q_9W_EGaC3gCoAEC","comment":"aniwaaa wayasa paatai godaaak.  wayasaka aya ekka giyaama naaki paata wenawaa kiyanne aththamai aneee...","author":"Renuka Silva","likeCount":1,"totalReplyCount":0,"publishedAt":"2017-03-09T17:51:15.000Z","replies":[]},{"id":"UggOvvjNnamgT3gCoAEC","comment":"ape rate saradarma walata bawdada saskruthiyata mewa galapen na.kohomada loku daruwo issaraha hasirenne.dawasaka.dawasaka demapiyanta dewani wiwahayak ona unot daruwanta magul.porut hadanna wey.","author":"Anulla Aaa","likeCount":0,"totalReplyCount":7,"publishedAt":"2017-03-09T17:50:08.000Z","replies":[{"parentId":"UggOvvjNnamgT3gCoAEC","authorDisplayName":"Anulla Aaa","replyComment":"Subasine suba Subasine...sanjeetha madayayen minisunge hama angayakma itha suksama lesa kiyapana minissu mewa e samajeta  own nogalapena nisa.","publishedAt":"2017-03-26T15:01:54.000Z","likeCount":0},{"parentId":"UggOvvjNnamgT3gCoAEC","authorDisplayName":"Subasine suba Subasine","replyComment":"katwath.mokada.auaga.kamatha.","publishedAt":"2017-03-26T14:57:56.000Z","likeCount":0},{"parentId":"UggOvvjNnamgT3gCoAEC","authorDisplayName":"Dona Dona","replyComment":"ane.paw.wektar.ratnayak.sar\nkisi.kenek.dos.kiyana.akak.naha\nayage.sindu.nawata.nawatat.\nahanawa.namama.n.suba.patanawa.wayasa.bala.panne.naha.adarayakata.deweyange.pihitai.dennatama","publishedAt":"2017-03-18T17:02:25.000Z","likeCount":0},{"parentId":"UggOvvjNnamgT3gCoAEC","authorDisplayName":"Zebiba Yimam","replyComment":"anuge,,kunu,,hoynne,apy,,lankve,,ganu,,minnsu,,wetri,,,topi,,harida,,balaphla,,oktoma,,esrha,,wela,,dan,,,apy,,lankve,,,podi,,kollo,,naki,,ganu,,aran,,hotel,,yanne,,budiynna,,topita,,ava,hodai,,,a,,depalta,mn,,suba,,pathanva,,,,,anunta,,mda,,ghnna,,apa,,sakkkiy,,balllo,,,balliyo,,,topy,,,yata,,,eka,,,balapn,,mulinma,,,kunu,,wealda,,,kiyla,,,,ke,,denek,,da,,kiyla,,,,,,","publishedAt":"2017-03-11T20:21:11.000Z","likeCount":0},{"parentId":"UggOvvjNnamgT3gCoAEC","authorDisplayName":"Ayesha 2015","replyComment":"60 peynnath waduro gas uda kiyanney meywata thamai😉😉😉","publishedAt":"2017-03-11T18:56:46.000Z","likeCount":0},{"parentId":"UggOvvjNnamgT3gCoAEC","authorDisplayName":"kiwait sreelanka","replyComment":"lankawa..inna.batkan.harakna.ahinda.untama.hodai.mawa","publishedAt":"2017-03-10T14:04:59.000Z","likeCount":0},{"parentId":"UggOvvjNnamgT3gCoAEC","authorDisplayName":"kiwait sreelanka","replyComment":"onna.ratata.adarsa.mat.minissu","publishedAt":"2017-03-10T08:54:28.000Z","likeCount":2}]},{"id":"UgilTkySYAMgw3gCoAEC","comment":"kamak ne subamagalam aka tamage kemetha","author":"Damika Desilva","likeCount":3,"totalReplyCount":3,"publishedAt":"2017-03-09T17:49:58.000Z","replies":[{"parentId":"UgilTkySYAMgw3gCoAEC","authorDisplayName":"roshita dickson","replyComment":"පුන්චි හිතුවක්කාරයා w WB","publishedAt":"2018-06-09T03:55:31.000Z","likeCount":0},{"parentId":"UgilTkySYAMgw3gCoAEC","authorDisplayName":"roshita dickson","replyComment":"Damika Desilva but","publishedAt":"2018-06-09T00:07:51.000Z","likeCount":0},{"parentId":"UgilTkySYAMgw3gCoAEC","authorDisplayName":"පුන්චි හිතුවක්කාරයා","replyComment":"Damika Desilva ඔව් මමත් කියන්නෙ ඒක","publishedAt":"2017-03-09T20:34:28.000Z","likeCount":2}]},{"id":"UgjH6Hua0nDxYXgCoAEC","comment":"kamak ne eka  loku deyak nemai eyaga kamaththa","author":"warnakula suriya","likeCount":2,"totalReplyCount":0,"publishedAt":"2017-03-09T17:40:36.000Z","replies":[]},{"id":"UghX8VZilsUOWHgCoAEC","comment":"mona 33 mekita 58 withara","author":"ramani malwatta","likeCount":40,"totalReplyCount":28,"publishedAt":"2017-03-09T17:36:58.000Z","replies":[{"parentId":"UghX8VZilsUOWHgCoAEC","authorDisplayName":"Manga Manga","replyComment":"@tak tukoක්","publishedAt":"2019-02-20T12:02:36.000Z","likeCount":0},{"parentId":"UghX8VZilsUOWHgCoAEC","authorDisplayName":"ParisTours Shuttle","replyComment":"Oyata tiyana Amaruwa mokakda.sihala budagame ayage palaweni eka anunge opadupa hoyanne,  watha sudda karaganna e welawe dengu maduruwo vinasa karaganna.","publishedAt":"2018-01-28T04:21:04.000Z","likeCount":0},{"parentId":"UghX8VZilsUOWHgCoAEC","authorDisplayName":"Mahinda Surasinghe","replyComment":"ramani malwatt","publishedAt":"2017-11-25T15:17:11.000Z","likeCount":0},{"parentId":"UghX8VZilsUOWHgCoAEC","authorDisplayName":"Damith De Silva","replyComment":"Damaki Kw ඔයා කෑල්ල උනා කියලා හැමෝම එහෙම වෙන්නෙ නෑ  සුවිටි ඩාලිං...😉","publishedAt":"2017-05-04T16:46:26.000Z","likeCount":0},{"parentId":"UghX8VZilsUOWHgCoAEC","authorDisplayName":"Damaki Kw","replyComment":"Damith De Silva අම්මා කෑල්ලක් වෙච්ච ඵකේ තරම තමයි පෙන් නුම් කරන්නේ","publishedAt":"2017-05-04T16:25:45.000Z","likeCount":0},{"parentId":"UghX8VZilsUOWHgCoAEC","authorDisplayName":"Damith De Silva","replyComment":"Damaki Kw Victor ගෙ කෙල්ල කෙල්ලෙක්...ඔයා කෑල්ලක්","publishedAt":"2017-05-04T13:42:11.000Z","likeCount":0},{"parentId":"UghX8VZilsUOWHgCoAEC","authorDisplayName":"Damaki Kw","replyComment":"Damith De Silva මේකිට කෙල්ල කියනවානම්  කෙල්ලන්ට මොකක්ද කියන්නේ","publishedAt":"2017-05-04T13:36:57.000Z","likeCount":0},{"parentId":"UghX8VZilsUOWHgCoAEC","authorDisplayName":"Ml Jaccob","replyComment":"Damith De Silva \np","publishedAt":"2017-04-19T23:40:27.000Z","likeCount":0},{"parentId":"UghX8VZilsUOWHgCoAEC","authorDisplayName":"Damith De Silva","replyComment":"ramani malwatta ..කෙල්ල ලස්සන නිසා තවත් රෛ්ෂ්‍යාවෙන් පෙලෙන කාන්තාවක්","publishedAt":"2017-04-14T07:13:35.000Z","likeCount":3},{"parentId":"UghX8VZilsUOWHgCoAEC","authorDisplayName":"wekara yas","replyComment":"ramani malwatta oya nam Mara ereseyawan enna ai occara kanteyan","publishedAt":"2017-03-15T10:57:48.000Z","likeCount":1},{"parentId":"UghX8VZilsUOWHgCoAEC","authorDisplayName":"NAS MAL","replyComment":"Piyal Modara  NIYAMA PRASHNEYAK PIYAL,KAWADAWATH UTTARA DENNE NETI,","publishedAt":"2017-03-15T07:51:32.000Z","likeCount":0},{"parentId":"UghX8VZilsUOWHgCoAEC","authorDisplayName":"Piyal Modara","replyComment":"ramani malwatta ramani oyaga wayasa kiyada","publishedAt":"2017-03-14T22:57:51.000Z","likeCount":0},{"parentId":"UghX8VZilsUOWHgCoAEC","authorDisplayName":"Piyal Modara","replyComment":"ramani malwatta oya kamthi nda","publishedAt":"2017-03-14T22:56:52.000Z","likeCount":0},{"parentId":"UghX8VZilsUOWHgCoAEC","authorDisplayName":"Nik Mini","replyComment":"eka aththa","publishedAt":"2017-03-14T19:09:41.000Z","likeCount":0},{"parentId":"UghX8VZilsUOWHgCoAEC","authorDisplayName":"Akash Rasanjana","replyComment":"ramani malwatta apo eka nam aththa thamai bnnnn","publishedAt":"2017-03-14T09:20:41.000Z","likeCount":0},{"parentId":"UghX8VZilsUOWHgCoAEC","authorDisplayName":"Akash Rasanjana","replyComment":"ramani malwatta apo eka nam aththa thamai bnnnn","publishedAt":"2017-03-14T09:20:34.000Z","likeCount":0},{"parentId":"UghX8VZilsUOWHgCoAEC","authorDisplayName":"Piyal Modara","replyComment":"ramani malwatta hi","publishedAt":"2017-03-12T23:30:38.000Z","likeCount":0},{"parentId":"UghX8VZilsUOWHgCoAEC","authorDisplayName":"wekara yas","replyComment":"ramani malwatta really","publishedAt":"2017-03-12T04:27:57.000Z","likeCount":0},{"parentId":"UghX8VZilsUOWHgCoAEC","authorDisplayName":"WG w.Upali","replyComment":"ramani malwatta","publishedAt":"2017-03-11T06:44:59.000Z","likeCount":1},{"parentId":"UghX8VZilsUOWHgCoAEC","authorDisplayName":"WG w.Upali","replyComment":"ramani malwatta","publishedAt":"2017-03-11T06:44:42.000Z","likeCount":0},{"parentId":"UghX8VZilsUOWHgCoAEC","authorDisplayName":"kithsara Whs","replyComment":"Ramyalatha Wanshadipathi Dewage ..........හොරා කන්න නම් ඔය කොයි පලාතත් හොදයි.. යන්තර මන්තර ගුරුකම් මතර තියෙනව තමයි..ඉස්සර මිනිස්සු ඒව හොද විඩියටයි පාවිච්චි කලේ..දැන් මිනිස්සු ඒව තමන්ගෙ වැරදි වැඩවලට යොදගන්නවා.. මාතරට අපහාස කරන්නෙපා..කොහේවත් නැති එවුන් කරන වැඩ නිසා","publishedAt":"2017-03-11T03:38:31.000Z","likeCount":0},{"parentId":"UghX8VZilsUOWHgCoAEC","authorDisplayName":"Jayalal Virasoriya","replyComment":"victor victor ma tama...prasnayak ne....","publishedAt":"2017-03-11T02:46:40.000Z","likeCount":0},{"parentId":"UghX8VZilsUOWHgCoAEC","authorDisplayName":"tak tuk","replyComment":"ramani malwatta .kiyala wedak naha .mona 33 da.hariyatam 60k vithara neda.kese wethath herak kiyala penawa .hora kamee saha huuniyame upatha maatara","publishedAt":"2017-03-10T14:10:44.000Z","likeCount":4},{"parentId":"UghX8VZilsUOWHgCoAEC","authorDisplayName":"NAS MAL","replyComment":"Sweeny Fernando \"  No one\"Thank you👍👍👍🌹🌹","publishedAt":"2017-03-10T14:06:16.000Z","likeCount":2},{"parentId":"UghX8VZilsUOWHgCoAEC","authorDisplayName":"Sweeny Fernando","replyComment":"jealousy & hypocrisy..ramani","publishedAt":"2017-03-10T14:01:32.000Z","likeCount":1},{"parentId":"UghX8VZilsUOWHgCoAEC","authorDisplayName":"Damayanthi rajapakshe Rajapakshe","replyComment":"ramani malwatta kiyala W adak ne. naki kolam","publishedAt":"2017-03-10T13:27:39.000Z","likeCount":1},{"parentId":"UghX8VZilsUOWHgCoAEC","authorDisplayName":"S S","replyComment":"mamath ahemai","publishedAt":"2017-03-09T21:35:35.000Z","likeCount":1},{"parentId":"UghX8VZilsUOWHgCoAEC","authorDisplayName":"kviv cjvv","replyComment":"mama  godak  gaurawa  karapu  gayakayen.  numut  mewa   dakkata  passe  pirimi  jatiyama  tittha  una.","publishedAt":"2017-03-09T20:25:43.000Z","likeCount":5}]},{"id":"Ugh-iLX_sy74-XgCoAEC","comment":"thathala puthala munupuran ekata diga kana yugayath pahala wigena enawa.","author":"Anulla Aaa","likeCount":1,"totalReplyCount":0,"publishedAt":"2017-03-09T17:27:06.000Z","replies":[]},{"id":"UghGsRfsb9lSbHgCoAEC","comment":"කමක් නැහ හොදයි .මේවා මහා ලොකු දෙවල් නොවේ ..තේරුවන්සරණයි","author":"Tusitana thusitha","likeCount":8,"totalReplyCount":1,"publishedAt":"2017-03-09T17:22:55.000Z","replies":[{"parentId":"UghGsRfsb9lSbHgCoAEC","authorDisplayName":"Pancha Promodya","replyComment":"Tusitana thusitha ubata.aekawalle paolda","publishedAt":"2017-03-09T18:53:37.000Z","likeCount":1}]},{"id":"UghJYxELDacEtHgCoAEC","comment":"ප්‍රස්නයක් නෑ ඉතින් ඒක එයාගෙ පුද්ගලික කැමැත්ත.... ඊට වඩා ලොකු ප්‍රස්න මේ රටේ තියෙන්නෙ..","author":"Hemantha sisira kumara Jhs","likeCount":95,"totalReplyCount":36,"publishedAt":"2017-03-09T17:08:39.000Z","replies":[{"parentId":"UghJYxELDacEtHgCoAEC","authorDisplayName":"Mahinda Surasinghe","replyComment":"Hemantha sisira kumara Jhs","publishedAt":"2017-11-25T15:14:25.000Z","likeCount":0},{"parentId":"UghJYxELDacEtHgCoAEC","authorDisplayName":"N රත්නායක kandy","replyComment":"Hemantha sisira kumara Jhs එකනම් ඇත්ත","publishedAt":"2017-08-19T11:44:54.000Z","likeCount":1},{"parentId":"UghJYxELDacEtHgCoAEC","authorDisplayName":"Devika Prasadani","replyComment":"+නිෂාන් දීපාල් l loo pppppq","publishedAt":"2017-07-01T17:53:12.000Z","likeCount":0},{"parentId":"UghJYxELDacEtHgCoAEC","authorDisplayName":"Hemantha sisira kumara Jhs","replyComment":"👏👏👏 ","publishedAt":"2017-06-09T08:04:00.000Z","likeCount":1},{"parentId":"UghJYxELDacEtHgCoAEC","authorDisplayName":"නිෂාන් සුගතදාස Nishan Sugathadasa","replyComment":"Hemantha sisira kumara Jhs නියමයි මල්ලි. ජපන්නු ජපන් වලින් වැඩකරගන්නවා. එංගලන්තෙ උන් උන්ගේ මවු බසින් රට හදාගන්නවා. රුස්සෝ රුසියානු බාසාවේන රොකට් හදනවා. අපේ උන්ට තමයි ඔය කඩ්ඩෙ කැසිල්ල තියෙන්නේ. කඩ්ඩ දාලා දිනන්න හදන නෝන්ඩි උන. නියමෙට කියුවා මල්ලි. ආඩම්බරයි. අපි අපේ දෙයින් ගොඩ එමු.","publishedAt":"2017-06-09T07:09:47.000Z","likeCount":0},{"parentId":"UghJYxELDacEtHgCoAEC","authorDisplayName":"නිෂාන් සුගතදාස Nishan Sugathadasa","replyComment":"අනිවාරයෙන්ම.","publishedAt":"2017-06-09T07:00:13.000Z","likeCount":0},{"parentId":"UghJYxELDacEtHgCoAEC","authorDisplayName":"nalaka nenaruwan","replyComment":"Hemantha sisira kumara Jhs","publishedAt":"2017-06-09T06:36:48.000Z","likeCount":0},{"parentId":"UghJYxELDacEtHgCoAEC","authorDisplayName":"නිෂාන් සුගතදාස Nishan Sugathadasa","replyComment":"එකඟයි. දෙන්නා කැමතිනම් ඕන දෙයක්.","publishedAt":"2017-03-15T19:51:37.000Z","likeCount":4},{"parentId":"UghJYxELDacEtHgCoAEC","authorDisplayName":"Kavindya Nethmini","replyComment":"'","publishedAt":"2017-03-14T10:09:22.000Z","likeCount":0},{"parentId":"UghJYxELDacEtHgCoAEC","authorDisplayName":"nnn","replyComment":"hadissiyakatawath podi lamai balaganda deelaa yanawa ehema nemei honday","publishedAt":"2017-03-13T09:31:14.000Z","likeCount":1},{"parentId":"UghJYxELDacEtHgCoAEC","authorDisplayName":"Madawa WijerthnA","replyComment":"ඒක ඇත්ත","publishedAt":"2017-03-12T21:45:19.000Z","likeCount":3},{"parentId":"UghJYxELDacEtHgCoAEC","authorDisplayName":"Richard Perera","replyComment":"Thanuja LANKA","publishedAt":"2017-03-11T07:33:57.000Z","likeCount":0},{"parentId":"UghJYxELDacEtHgCoAEC","authorDisplayName":"Thanuja Lakmali","replyComment":"Hashan Priyanath m...m...wayata nemei wada chi...","publishedAt":"2017-03-11T00:52:32.000Z","likeCount":3},{"parentId":"UghJYxELDacEtHgCoAEC","authorDisplayName":"Hemantha sisira kumara Jhs","replyComment":"මන් ඉංග්‍රීසි නම් දන් නෑ.මට හිතෙන්නෙ ඔයා එතුමගෙ තරහ කාරියක්.වික්ටර් මහතාගේ සන්ගීතය විතරක් ඔයා ගන්න.පෞද්ගලික ප්‍රස්න අදාල කර නොගන්නව නම් තමයි හොද.එයාලට නැති ප්‍රස්න ඔයාට කොහෙන්ද.....  😂😂","publishedAt":"2017-03-10T23:43:07.000Z","likeCount":2},{"parentId":"UghJYxELDacEtHgCoAEC","authorDisplayName":"yashoodara h","replyComment":"mind your business . this is true.if you don't accept it is your business. but I said really true. if you have good mind think. if you don't have good mind you will think you are win.i don't care. but have been see this really life ","publishedAt":"2017-03-10T22:41:13.000Z","likeCount":0},{"parentId":"UghJYxELDacEtHgCoAEC","authorDisplayName":"Hemantha sisira kumara Jhs","replyComment":"මට තේරෙන විදියට ඔයත් නිකම් කොහෙ හරි රට කට ගිහින් බොරු posh ගති පෙන්නන්න හදනව වගේ.කූඩැල්ලො මෙට්ටෙ තියන්න බෑ යාලු.පොලවෙ පය  ගහල තමන්ගෙ දෙයක් බලා ගෙන ඉන්න.ගොන් ටෝක් දීල පොර වෙන්න හදන්න එපා.","publishedAt":"2017-03-10T22:37:46.000Z","likeCount":1},{"parentId":"UghJYxELDacEtHgCoAEC","authorDisplayName":"yashoodara h","replyComment":"ma modaya samajaye wagakimak darana kanak.apita kagawath life akak wadak na.habe ma nakiya nikan gama gode inna kasippu karayak unannam","publishedAt":"2017-03-10T22:33:45.000Z","likeCount":1},{"parentId":"UghJYxELDacEtHgCoAEC","authorDisplayName":"Hemantha sisira kumara Jhs","replyComment":"මන් ලොජික් දාන් නෑ හලෝ.ඔයානේ අනුන්ගෙ ප්‍රස්නයක් අරන් දගලන්නෙ.ඔයාට මොකද්ද ඔය තරම් ඒ ගැන තියෙන කැක්කුම? ගොනෙක් වගේ එයාගෙ පුද්ගලික ජීවිතේ ප්‍රස්න ඔයා ප්‍රස්නයක් කර ගන්න එපා.වික්ටර් කියන ගායකයට විතරක් ගරු කරන්න.","publishedAt":"2017-03-10T22:33:36.000Z","likeCount":2},{"parentId":"UghJYxELDacEtHgCoAEC","authorDisplayName":"yashoodara h","replyComment":"ma 2 gan daruwek hitiyoth athakota mokada karanna?uropcuntry akak unanam daruwa nat karanna puluwan.tawa nakiyo 100k hari marry karannath puluwan. ath maka sri lankawa","publishedAt":"2017-03-10T22:31:32.000Z","likeCount":1},{"parentId":"UghJYxELDacEtHgCoAEC","authorDisplayName":"yashoodara h","replyComment":"open cantry akak unanam oyage logic ape ratata hariyanawa.dan ma nakiya maruna data ma kalla thawa math tharunai.athakota mokada karanna","publishedAt":"2017-03-10T22:29:34.000Z","likeCount":1},{"parentId":"UghJYxELDacEtHgCoAEC","authorDisplayName":"yashoodara h","replyComment":"mr hamantha oyama nada kiuwe ape rate ona tharam problem tiyanawa kiyala gon dakata logic danna epa math akka","publishedAt":"2017-03-10T22:27:28.000Z","likeCount":1},{"parentId":"UghJYxELDacEtHgCoAEC","authorDisplayName":"Hemantha sisira kumara Jhs","replyComment":"එයා වයසක බව ඇත්ත.. මැරුනම එයා කැමති තීරනයක් ගනී.ඒ හැමදේම හිතලනෙ බදින්න ඇත්තෙ.මනුස්සෙක්ට ජීවත් වෙන්න බදින්නම ඕන නෑ.එහෙම නම්  හදිස්සියෙවත් ඔයාලයි තාත්ත මැරුනොත් අම්ම වෙන මිනිහෙක් එක්ක යනවද තනියම ඉන්න බෑ කියල? අනික ඒ මනුස්සයා සමාජයේ කැපී පේන්නෙ ගායකයෙක් වශයෙන් විතරයි.බැන්ද කියල ගායන දිවියට ප්‍රස්නයක් උන් නෑනෙ.එයාගෙ පුද්ගලික ජීවිතේට ඇගිලි ගහන්න එපා.","publishedAt":"2017-03-10T22:24:43.000Z","likeCount":1},{"parentId":"UghJYxELDacEtHgCoAEC","authorDisplayName":"yashoodara h","replyComment":"Dakala tiyanawa da Ahama ayage anagathe a gollangan behiuna daruwo ","publishedAt":"2017-03-10T22:19:23.000Z","likeCount":0},{"parentId":"UghJYxELDacEtHgCoAEC","authorDisplayName":"Hemantha sisira kumara Jhs","replyComment":"නොමැරෙන මිනිස්සු නෑ yashoodara.අපි හැමෝම මැරෙනව.ඒත් එහෙම හිතල අපි නොබැද ඉන්නෙ නෑනෙ.ඊට වඩා ලොකු වයස් පරතරවල ඉන්න අය බදිනව.ඒක එයාලට ප්‍රස්නයක් නෙවෙයි නම් ඇයි ඔයා ප්‍රස්නයක් කර ගන්නෙ? ","publishedAt":"2017-03-10T22:12:50.000Z","likeCount":1},{"parentId":"UghJYxELDacEtHgCoAEC","authorDisplayName":"yashoodara h","replyComment":"maka sinhala baudda ratak.man uropcuntry akaka jiwath walath ma wage gobba adahas awe ne","publishedAt":"2017-03-10T22:12:40.000Z","likeCount":0},{"parentId":"UghJYxELDacEtHgCoAEC","authorDisplayName":"yashoodara h","replyComment":"anika samajaye kapi panana minissu mita wada wagakiman samajaya idiriye hitaganna ona","publishedAt":"2017-03-10T22:10:06.000Z","likeCount":0},{"parentId":"UghJYxELDacEtHgCoAEC","authorDisplayName":"yashoodara h","replyComment":"moda widihata hithanna epa mr Hemantha.ma moda nakiya maruna dakat oyada a girl wa baraganna","publishedAt":"2017-03-10T22:08:51.000Z","likeCount":0},{"parentId":"UghJYxELDacEtHgCoAEC","authorDisplayName":"Hemantha sisira kumara Jhs","replyComment":"හ්ම් හ්ම්ම්ම්....","publishedAt":"2017-03-10T21:14:36.000Z","likeCount":0},{"parentId":"UghJYxELDacEtHgCoAEC","authorDisplayName":"Geethika Kumuduni Jayasinghe","replyComment":"Hemantha sisira kumara Jhs eka aththa","publishedAt":"2017-03-10T19:11:09.000Z","likeCount":1},{"parentId":"UghJYxELDacEtHgCoAEC","authorDisplayName":"nimali adirisinha","replyComment":"akaa attaaaa","publishedAt":"2017-03-10T09:13:18.000Z","likeCount":2},{"parentId":"UghJYxELDacEtHgCoAEC","authorDisplayName":"Chandhi Chandhi","replyComment":"Hemantha sisira kumara Jhs hareyatama  hare\noyage  katavanam\nmeta  vada  deval  venni  nadda  api  rate....","publishedAt":"2017-03-09T22:40:12.000Z","likeCount":4},{"parentId":"UghJYxELDacEtHgCoAEC","authorDisplayName":"Hemantha sisira kumara Jhs","replyComment":"හ්ම්ම්ම්ම්............  FB එක youtube එක තමයි දැන් රටේම ප්‍රස්න විසදන තැන.තමන්ගෙ පුද්ගලික ප්‍රස්න සමාජ ජාල වල නොදා ඉන්නව නම් තමයි හොද.","publishedAt":"2017-03-09T20:52:19.000Z","likeCount":10},{"parentId":"UghJYxELDacEtHgCoAEC","authorDisplayName":"පුන්චි හිතුවක්කාරයා","replyComment":"Hemantha sisira kumara Jhs ඔව් අනේ කාටවත් ඇගිල්ල දික් කරන අය හොද අය නෙවෙයි ලෝකේ තියන ලොකුම වරද කරන්නෙ එයාලා  මොකක්ද වරද අනුන්ට ඇගිල්ල දික් කරන එක","publishedAt":"2017-03-09T20:27:33.000Z","likeCount":1},{"parentId":"UghJYxELDacEtHgCoAEC","authorDisplayName":"පුන්චි හිතුවක්කාරයා","replyComment":"Hemantha sisira kumara හ්ම්","publishedAt":"2017-03-09T20:24:27.000Z","likeCount":1},{"parentId":"UghJYxELDacEtHgCoAEC","authorDisplayName":"Pancha Promodya","replyComment":"Hemantha sisira kumara Jhs aekawalle pol wage","publishedAt":"2017-03-09T18:55:07.000Z","likeCount":1},{"parentId":"UghJYxELDacEtHgCoAEC","authorDisplayName":"kanchana dombagolle","replyComment":"Hemantha sisira kumara Jhs salli theyenawanam eyata kanna bonna adainna paladinna denna puluwannam dekak barinam thuna hatharakwath badagaththden apata moko.","publishedAt":"2017-03-09T18:49:45.000Z","likeCount":2}]},{"id":"Ugg_x90_Fh488XgCoAEC","comment":"ape ratata giya kalak","author":"Sisira Kumara","likeCount":1,"totalReplyCount":0,"publishedAt":"2017-03-09T17:04:47.000Z","replies":[]},{"id":"UggIbY_Mlfx-J3gCoAEC","comment":"echcharama loku paratharayak penne naha.33k neweyi 50k wage penanawa","author":"tak tuk","likeCount":23,"totalReplyCount":1,"publishedAt":"2017-03-09T16:49:42.000Z","replies":[{"parentId":"UggIbY_Mlfx-J3gCoAEC","authorDisplayName":"Jayaratne Abeydeera","replyComment":"ඒනම් ඉරිසියාවටම කියන  කතාවක්෴","publishedAt":"2017-03-16T17:34:07.000Z","likeCount":2}]}]}]